Workbook
Name Slicer_Age_Group_Class: #N/A
Name Slicer_Date_Year: #N/A
Name Slicer_MD_Short: #N/A
Name Slicer_Risk_Tier: #N/A
Name Slicer_Short_Month: #N/A

Sheet Pivots
A3: Total Appointment | E3: Total Revenue | I3: Total Operational Cost | M3: Total Overtime Hours
A4: 2505 | E4: 22826272 | I4: 15473835 | M4: 21025.4
G5: [$$-en-US][>=1000000]#,##0.00,,"M";[>=1000#,##0.0,"K";#,##0
A8: Department | B8: Total Appointment | E8: Months | F8: Total Revenue | I8: Department | J8: Total Revenue | M8: Age Group | N8: Total Appointment
A9: Cardio | B9: 342 | E9: Jan | F9: 1749341.3 | I9: Cardiology | J9: 3245463.5 | M9: Adult | N9: 1287
A10: ICU | B10: 341 | E10: Feb | F10: 1846072.3 | I10: Emergency Room | J10: 2190568.7 | M10: Geriatric | N10: 900
A11: Neuro | B11: 330 | E11: Mar | F11: 1996281.7 | I11: General Medicine | J11: 1009094.8 | M11: Pediatric | N11: 318
A12: ER | B12: 319 | E12: Apr | F12: 2008475.3 | I12: Intensive Care Unit | J12: 5587597.8
A13: PD | B13: 301 | E13: May | F13: 2188857.8 | I13: Neurology | J13: 3006250.4
A14: Surgery | B14: 298 | E14: Jun | F14: 2162640.2 | I14: Orthopedics | J14: 2201025.7
A15: GM | B15: 293 | E15: Jul | F15: 2007985.2 | I15: Pediatrics | J15: 522488.67
A16: Ortho | B16: 281 | E16: Aug | F16: 1235909 | I16: Surgery | J16: 5063782.7
E17: Sep | F17: 1749732 | M17: Clinical Status | N17: Total Appointment
A18: Month | B18: Count of Patient_ID | E18: Oct | F18: 2014370.2 | M18: Discharged | N18: 0.54730539
A19: Jan | B19: 209 | E19: Nov | F19: 1817058.9 | M19: In-Patient Care | N19: 0.28303393
A20: Feb | B20: 214 | E20: Dec | F20: 2049548.4 | I20: Row Labels | J20: Sum of Staff_Overtime_Hrs | M20: Readmitted | N20: 0.16966068
A21: Mar | B21: 219 | I21: 2023 | J21: 2296
A22: Apr | B22: 226 | I22: 2024 | J22: 7181
A23: May | B23: 236 | I23: 2025 | J23: 7418 | L23: Year | M23: Operational Cost | N23: Revenue
A24: Jun | B24: 233 | I24: 2026 | J24: 4130.4 | L24: 2026 | M24: 3052325.9 | N24: 4516068.9
A25: Jul | B25: 210 | I25: Grand Total | J25: 21025.4 | L25: 2025 | M25: 5541248.5 | N25: 8177217.5
A26: Aug | B26: 135 | L26: 2024 | M26: 5167705.1 | N26: 7606763.7
A27: Sep | B27: 187 | L27: 2023 | M27: 1712555.4 | N27: 2526222.3
A28: Oct | B28: 209 | L28: Grand Total | M28: 15473835 | N28: 22826272
A29: Nov | B29: 198
A30: Dec | B30: 229
A31: Grand Total | B31: 2505

Sheet KPI
B10: 1) Total Appointment | C10: =GETPIVOTDATA("Patient_ID",Pivots!$A$3) -> 2505
B11: 2) Total Revenue | C11: =GETPIVOTDATA("Patient_Bill",Pivots!$E$3) -> 22826272
B12: 3) Total Operational Cost | C12: =GETPIVOTDATA("Operational_Cost",Pivots!$I$3) -> 15473835
B13: 4) Total Profit | C13: =C11-C12 -> 7352437.5
B14: 5) Total Staff Overtime | C14: =GETPIVOTDATA("Staff_Overtime_Hrs",Pivots!$M$3) -> 21025.4
B16: Patient Across Department
B17: Monthly Revenue
B18: Departmental Revenue
B19: Age Group By Appointment
B20: Clinical Status By Appointment

Sheet Patient_Data
A1: Patient_ID | B1: Month | C1: Short_Month | D1: Month_Num | E1: Admission_Date | F1: Date_Year | G1: Patient_Name | H1: Facility_Name | I1: Gender | J1: Age | K1: Clinical_Status | L1: CareStage | M1: Medical_Department | N1: MD_Short | O1: Patient_Bill | P1: Operational_Cost | Q1: Staff_Overtime_Hrs | R1: Risk_Tier | S1: Age_Group_Class
A2: NHM-2024-102404 | B2: =TEXT(Patient_Data!$E2,"mmmm") -> April | C2: =LEFT(B2,3) -> Apr | D2: =MONTH(Patient_Data!$E2) -> 4 | E2: 45395 | F2: =TEXT(Patient_Data[[#This Row],[Admission_Date]],"YYYY") -> 2024 | G2: Albert King | H2: NovaHealth Chicago Medical Center | I2: Male | J2: 30 | K2: Discharged | L2: 1 | M2: Neurology | N2: =IF(M2="Cardiology","Cardio",IF(M2="Intensive Care Unit","ICU",IF(M2="Neurology","Neuro",IF(M2="Emergency Room","ER",IF(M2="Pediatrics","PD",IF(M2="Surgery","Surgery",IF(M2="General Medicine","GM",IF(M2="Orthopedics","Ortho","")))))))) -> Neuro | O2: 9382.46 | P2: 6022.37 | Q2: 2.2 | R2: =IF(Patient_Data!$L2<2,"Low Risk",IF(Patient_Data!$L2<4,"Moderate Risk","High Risk")) -> Low Risk | S2: =IF(Patient_Data[[#This Row],[Age]]<=18,"Pediatric",IF(Patient_Data[[#This Row],[Age]]<=64,"Adult","Geriatric")) -> Adult
A3: NHM-2026-102164 | B3: =TEXT(Patient_Data!$E3,"mmmm") -> March | C3: =LEFT(B3,3) -> Mar | D3: =MONTH(Patient_Data!$E3) -> 3 | E3: 45730 | F3: =TEXT(Patient_Data[[#This Row],[Admission_Date]],"YYYY") -> 2025 | G3: Cynthia Clark | H3: NovaHealth Lakeside Medical Center | I3: Female | J3: 48 | K3: Discharged | L3: 1 | M3: Cardiology | N3: =IF(M3="Cardiology","Cardio",IF(M3="Intensive Care Unit","ICU",IF(M3="Neurology","Neuro",IF(M3="Emergency Room","ER",IF(M3="Pediatrics","PD",IF(M3="Surgery","Surgery",IF(M3="General Medicine","GM",IF(M3="Orthopedics","Ortho","")))))))) -> Cardio | O3: 8292.65 | P3: 5584.88 | Q3: 3.6 | R3: =IF(Patient_Data!$L3<2,"Low Risk",IF(Patient_Data!$L3<4,"Moderate Risk","High Risk")) -> Low Risk | S3: =IF(Patient_Data[[#This Row],[Age]]<=18,"Pediatric",IF(Patient_Data[[#This Row],[Age]]<=64,"Adult","Geriatric")) -> Adult
A4: NHM-2023-100823 | B4: =TEXT(Patient_Data!$E4,"mmmm") -> March | C4: =LEFT(B4,3) -> Mar | D4: =MONTH(Patient_Data!$E4) -> 3 | E4: 45376 | F4: =TEXT(Patient_Data[[#This Row],[Admission_Date]],"YYYY") -> 2024 | G4: Michelle Graham | H4: NovaHealth Chicago Medical Center | I4: Female | J4: 28 | K4: Discharged | L4: 2 | M4: General Medicine | N4: =IF(M4="Cardiology","Cardio",IF(M4="Intensive Care Unit","ICU",IF(M4="Neurology","Neuro",IF(M4="Emergency Room","ER",IF(M4="Pediatrics","PD",IF(M4="Surgery","Surgery",IF(M4="General Medicine","GM",IF(M4="Orthopedics","Ortho","")))))))) -> GM | O4: 4743.5 | P4: 3381.25 | Q4: 7.6 | R4: =IF(Patient_Data!$L4<2,"Low Risk",IF(Patient_Data!$L4<4,"Moderate Risk","High Risk")) -> Moderate Risk | S4: =IF(Patient_Data[[#This Row],[Age]]<=18,"Pediatric",IF(Patient_Data[[#This Row],[Age]]<=64,"Adult","Geriatric")) -> Adult
A5: NHM-2023-102060 | B5: =TEXT(Patient_Data!$E5,"mmmm") -> February | C5: =LEFT(B5,3) -> Feb | D5: =MONTH(Patient_Data!$E5) -> 2 | E5: 45345 | F5: =TEXT(Patient_Data[[#This Row],[Admission_Date]],"YYYY") -> 2024 | G5: Amy Hill | H5: NovaHealth Lakeshore Regional Center | I5: Female | J5: 70 | K5: Discharged | L5: 2 | M5: Cardiology | N5: =IF(M5="Cardiology","Cardio",IF(M5="Intensive Care Unit","ICU",IF(M5="Neurology","Neuro",IF(M5="Emergency Room","ER",IF(M5="Pediatrics","PD",IF(M5="Surgery","Surgery",IF(M5="General Medicine","GM",IF(M5="Orthopedics","Ortho","")))))))) -> Cardio | O5: 7138.49 | P5: 5267.1 | Q5: 7 | R5: =IF(Patient_Data!$L5<2,"Low Risk",IF(Patient_Data!$L5<4,"Moderate Risk","High Risk")) -> Moderate Risk | S5: =IF(Patient_Data[[#This Row],[Age]]<=18,"Pediatric",IF(Patient_Data[[#This Row],[Age]]<=64,"Adult","Geriatric")) -> Geriatric
A6: NHM-2025-101899 | B6: =TEXT(Patient_Data!$E6,"mmmm") -> January | C6: =LEFT(B6,3) -> Jan | D6: =MONTH(Patient_Data!$E6) -> 1 | E6: 46031 | F6: =TEXT(Patient_Data[[#This Row],[Admission_Date]],"YYYY") -> 2026 | G6: Evelyn Woods | H6: NovaHealth Chicago Medical Center | I6: Male | J6: 79 | K6: Readmitted | L6: 4 | M6: Orthopedics | N6: =IF(M6="Cardiology","Cardio",IF(M6="Intensive Care Unit","ICU",IF(M6="Neurology","Neuro",IF(M6="Emergency Room","ER",IF(M6="Pediatrics","PD",IF(M6="Surgery","Surgery",IF(M6="General Medicine","GM",IF(M6="Orthopedics","Ortho","")))))))) -> Ortho | O6: 9221.73 | P6: 7079.71 | Q6: 8.9 | R6: =IF(Patient_Data!$L6<2,"Low Risk",IF(Patient_Data!$L6<4,"Moderate Risk","High Risk")) -> High Risk | S6: =IF(Patient_Data[[#This Row],[Age]]<=18,"Pediatric",IF(Patient_Data[[#This Row],[Age]]<=64,"Adult","Geriatric")) -> Geriatric
A7: NHM-2026-101384 | B7: =TEXT(Patient_Data!$E7,"mmmm") -> November | C7: =LEFT(B7,3) -> Nov | D7: =MONTH(Patient_Data!$E7) -> 11 | E7: 45232 | F7: =TEXT(Patient_Data[[#This Row],[Admission_Date]],"YYYY") -> 2023 | G7: Michelle Martinez | H7: NovaHealth Midtown Medical Center | I7: Male | J7: 59 | K7: Readmitted | L7: 3 | M7: Intensive Care Unit | N7: =IF(M7="Cardiology","Cardio",IF(M7="Intensive Care Unit","ICU",IF(M7="Neurology","Neuro",IF(M7="Emergency Room","ER",IF(M7="Pediatrics","PD",IF(M7="Surgery","Surgery",IF(M7="General Medicine","GM",IF(M7="Orthopedics","Ortho","")))))))) -> ICU | O7: 18870.98 | P7: 11079.57 | Q7: 16.8 | R7: =IF(Patient_Data!$L7<2,"Low Risk",IF(Patient_Data!$L7<4,"Moderate Risk","High Risk")) -> Moderate Risk | S7: =IF(Patient_Data[[#This Row],[Age]]<=18,"Pediatric",IF(Patient_Data[[#This Row],[Age]]<=64,"Adult","Geriatric")) -> Adult
A8: NHM-2023-102093 | B8: =TEXT(Patient_Data!$E8,"mmmm") -> October | C8: =LEFT(B8,3) -> Oct | D8: =MONTH(Patient_Data!$E8) -> 10 | E8: 45228 | F8: =TEXT(Patient_Data[[#This Row],[Admission_Date]],"YYYY") -> 2023 | G8: Austin Webb | H8: NovaHealth Greenfield Clinic | I8: Female | J8: 91 | K8: In-Patient Care | L8: 5 | M8: Intensive Care Unit | N8: =IF(M8="Cardiology","Cardio",IF(M8="Intensive Care Unit","ICU",IF(M8="Neurology","Neuro",IF(M8="Emergency Room","ER",IF(M8="Pediatrics","PD",IF(M8="Surgery","Surgery",IF(M8="General Medicine","GM",IF(M8="Orthopedics","Ortho","")))))))) -> ICU | O8: 22963.46 | P8: 14094.11 | Q8: 10.8 | R8: =IF(Patient_Data!$L8<2,"Low Risk",IF(Patient_Data!$L8<4,"Moderate Risk","High Risk")) -> High Risk | S8: =IF(Patient_Data[[#This Row],[Age]]<=18,"Pediatric",IF(Patient_Data[[#This Row],[Age]]<=64,"Adult","Geriatric")) -> Geriatric
A9: NHM-2023-100762 | B9: =TEXT(Patient_Data!$E9,"mmmm") -> December | C9: =LEFT(B9,3) -> Dec | D9: =MONTH(Patient_Data!$E9) -> 12 | E9: 45643 | F9: =TEXT(Patient_Data[[#This Row],[Admission_Date]],"YYYY") -> 2024 | G9: Jacob Lee | H9: Nova Health Chicago Medical Center | I9: Male | J9: 38 | K9: Discharged | L9: 1 | M9: Cardiology | N9: =IF(M9="Cardiology","Cardio",IF(M9="Intensive Care Unit","ICU",IF(M9="Neurology","Neuro",IF(M9="Emergency Room","ER",IF(M9="Pediatrics","PD",IF(M9="Surgery","Surgery",IF(M9="General Medicine","GM",IF(M9="Orthopedics","Ortho","")))))))) -> Cardio | O9: 5217.55 | P9: 3364.83 | Q9: 3.2 | R9: =IF(Patient_Data!$L9<2,"Low Risk",IF(Patient_Data!$L9<4,"Moderate Risk","High Risk")) -> Low Risk | S9: =IF(Patient_Data[[#This Row],[Age]]<=18,"Pediatric",IF(Patient_Data[[#This Row],[Age]]<=64,"Adult","Geriatric")) -> Adult
A10: NHM-2026-102456 | B10: =TEXT(Patient_Data!$E10,"mmmm") -> October | C10: =LEFT(B10,3) -> Oct | D10: =MONTH(Patient_Data!$E10) -> 10 | E10: 45574 | F10: =TEXT(Patient_Data[[#This Row],[Admission_Date]],"YYYY") -> 2024 | G10: Theresa Ross | H10: NovaHealth Lakeside Medical Center | I10: Female | J10: 53 | K10: Discharged | L10: 1 | M10: Orthopedics | N10: =IF(M10="Cardiology","Cardio",IF(M10="Intensive Care Unit","ICU",IF(M10="Neurology","Neuro",IF(M10="Emergency Room","ER",IF(M10="Pediatrics","PD",IF(M10="Surgery","Surgery",IF(M10="General Medicine","GM",IF(M10="Orthopedics","Ortho","")))))))) -> Ortho | O10: 5182.32 | P10: 3506.55 | Q10: 4.3 | R10: =IF(Patient_Data!$L10<2,"Low Risk",IF(Patient_Data!$L10<4,"Moderate Risk","High Risk")) -> Low Risk | S10: =IF(Patient_Data[[#This Row],[Age]]<=18,"Pediatric",IF(Patient_Data[[#This Row],[Age]]<=64,"Adult","Geriatric")) -> Adult
A11: NHM-2025-100770 | B11: =TEXT(Patient_Data!$E11,"mmmm") -> March | C11: =LEFT(B11,3) -> Mar | D11: =MONTH(Patient_Data!$E11) -> 3 | E11: 45736 | F11: =TEXT(Patient_Data[[#This Row],[Admission_Date]],"YYYY") -> 2025 | G11: James Castillo | H11: NovaHealth Chicago Medical Center | I11: Male | J11: 35 | K11: Discharged | L11: 1 | M11: General Medicine | N11: =IF(M11="Cardiology","Cardio",IF(M11="Intensive Care Unit","ICU",IF(M11="Neurology","Neuro",IF(M11="Emergency Room","ER",IF(M11="Pediatrics","PD",IF(M11="Surgery","Surgery",IF(M11="General Medicine","GM",IF(M11="Orthopedics","Ortho","")))))))) -> GM | O11: 2381.2 | P11: 1702.84 | Q11: 4.5 | R11: =IF(Patient_Data!$L11<2,"Low Risk",IF(Patient_Data!$L11<4,"Moderate Risk","High Risk")) -> Low Risk | S11: =IF(Patient_Data[[#This Row],[Age]]<=18,"Pediatric",IF(Patient_Data[[#This Row],[Age]]<=64,"Adult","Geriatric")) -> Adult
A12: NHM-2025-101456 | B12: =TEXT(Patient_Data!$E12,"mmmm") -> September | C12: =LEFT(B12,3) -> Sep | D12: =MONTH(Patient_Data!$E12) -> 9 | E12: 45180 | F12: =TEXT(Patient_Data[[#This Row],[Admission_Date]],"YYYY") -> 2023 | G12: Sarah Diaz | H12: Nova Health Lakeshore Regional Center | I12: Male | J12: 42 | K12: Discharged | L12: 1 | M12: Neurology | N12: =IF(M12="Cardiology","Cardio",IF(M12="Intensive Care Unit","ICU",IF(M12="Neurology","Neuro",IF(M12="Emergency Room","ER",IF(M12="Pediatrics","PD",IF(M12="Surgery","Surgery",IF(M12="General Medicine","GM",IF(M12="Orthopedics","Ortho","")))))))) -> Neuro | O12: 8544.19 | P12: 6299.66 | Q12: 7.8 | R12: =IF(Patient_Data!$L12<2,"Low Risk",IF(Patient_Data!$L12<4,"Moderate Risk","High Risk")) -> Low Risk | S12: =IF(Patient_Data[[#This Row],[Age]]<=18,"Pediatric",IF(Patient_Data[[#This Row],[Age]]<=64,"Adult","Geriatric")) -> Adult
A13: NHM-2023-102375 | B13: =TEXT(Patient_Data!$E13,"mmmm") -> July | C13: =LEFT(B13,3) -> Jul | D13: =MONTH(Patient_Data!$E13) -> 7 | E13: 45863 | F13: =TEXT(Patient_Data[[#This Row],[Admission_Date]],"YYYY") -> 2025 | G13: Debra Brooks | H13: NovaHealth Chicago Medical Center | I13: Male | J13: 44 | K13: Discharged | L13: 2 | M13: Neurology | N13: =IF(M13="Cardiology","Cardio",IF(M13="Intensive Care Unit","ICU",IF(M13="Neurology","Neuro",IF(M13="Emergency Room","ER",IF(M13="Pediatrics","PD",IF(M13="Surgery","Surgery",IF(M13="General Medicine","GM",IF(M13="Orthopedics","Ortho","")))))))) -> Neuro | O13: 8917.69 | P13: 6828.64 | Q13: 6.4 | R13: =IF(Patient_Data!$L13<2,"Low Risk",IF(Patient_Data!$L13<4,"Moderate Risk","High Risk")) -> Moderate Risk | S13: =IF(Patient_Data[[#This Row],[Age]]<=18,"Pediatric",IF(Patient_Data[[#This Row],[Age]]<=64,"Adult","Geriatric")) -> Adult
... A95: NHM-2024-100495 | B95: =TEXT(Patient_Data!$E95,"mmmm") -> December | C95: =LEFT(B95,3) -> Dec | D95: =MONTH(Patient_Data!$E95) -> 12 | E95: 45627 | F95: =TEXT(Patient_Data[[#This Row],[Admission_Date]],"YYYY") -> 2024 | G95: Ann Gomez | H95: NovaHealth Oakridge Community Hospital | I95: Female | J95: 65 | K95: Readmitted | L95: 4 | M95: Surgery | N95: =IF(M95="Cardiology","Cardio",IF(M95="Intensive Care Unit","ICU",IF(M95="Neurology","Neuro",IF(M95="Emergency Room","ER",IF(M95="Pediatrics","PD",IF(M95="Surgery","Surgery",IF(M95="General Medicine","GM",IF(M95="Orthopedics","Ortho","")))))))) -> Surgery | O95: 11963.03 | P95: 8433.32 | Q95: 7.4 | R95: =IF(Patient_Data!$L95<2,"Low Risk",IF(Patient_Data!$L95<4,"Moderate Risk","High Risk")) -> High Risk | S95: =IF(Patient_Data[[#This Row],[Age]]<=18,"Pediatric",IF(Patient_Data[[#This Row],[Age]]<=64,"Adult","Geriatric")) -> Geriatric
A96: NHM-2026-100017 | B96: =TEXT(Patient_Data!$E96,"mmmm") -> October | C96: =LEFT(B96,3) -> Oct | D96: =MONTH(Patient_Data!$E96) -> 10 | E96: 45210 | F96: =TEXT(Patient_Data[[#This Row],[Admission_Date]],"YYYY") -> 2023 | G96: Joe Freeman | H96: NovaHealth Chicago Medical Center | I96: Female | J96: 84 | K96: In-Patient Care | L96: 4 | M96: Neurology | N96: =IF(M96="Cardiology","Cardio",IF(M96="Intensive Care Unit","ICU",IF(M96="Neurology","Neuro",IF(M96="Emergency Room","ER",IF(M96="Pediatrics","PD",IF(M96="Surgery","Surgery",IF(M96="General Medicine","GM",IF(M96="Orthopedics","Ortho","")))))))) -> Neuro | O96: 12745.26 | P96: 9304.04 | R96: =IF(Patient_Data!$L96<2,"Low Risk",IF(Patient_Data!$L96<4,"Moderate Risk","High Risk")) -> High Risk | S96: =IF(Patient_Data[[#This Row],[Age]]<=18,"Pediatric",IF(Patient_Data[[#This Row],[Age]]<=64,"Adult","Geriatric")) -> Geriatric
A97: NHM-2025-102343 | B97: =TEXT(Patient_Data!$E97,"mmmm") -> December | C97: =LEFT(B97,3) -> Dec | D97: =MONTH(Patient_Data!$E97) -> 12 | E97: 45638 | F97: =TEXT(Patient_Data[[#This Row],[Admission_Date]],"YYYY") -> 2024 | G97: Elizabeth Reed | H97: NovaHealth Chicago Medical Center | I97: Male | J97: 57 | K97: Readmitted | L97: 4 | M97: Intensive Care Unit | N97: =IF(M97="Cardiology","Cardio",IF(M97="Intensive Care Unit","ICU",IF(M97="Neurology","Neuro",IF(M97="Emergency Room","ER",IF(M97="Pediatrics","PD",IF(M97="Surgery","Surgery",IF(M97="General Medicine","GM",IF(M97="Orthopedics","Ortho","")))))))) -> ICU | O97: 14707.38 | P97: 11288.81 | Q97: 13.9 | R97: =IF(Patient_Data!$L97<2,"Low Risk",IF(Patient_Data!$L97<4,"Moderate Risk","High Risk")) -> High Risk | S97: =IF(Patient_Data[[#This Row],[Age]]<=18,"Pediatric",IF(Patient_Data[[#This Row],[Age]]<=64,"Adult","Geriatric")) -> Adult
A98: NHM-2026-100012 | B98: =TEXT(Patient_Data!$E98,"mmmm") -> November | C98: =LEFT(B98,3) -> Nov | D98: =MONTH(Patient_Data!$E98) -> 11 | E98: 45618 | F98: =TEXT(Patient_Data[[#This Row],[Admission_Date]],"YYYY") -> 2024 | G98: Jessica Castillo | H98: NovaHealth Greenfield Clinic | I98: Female | J98: 73 | K98: In-Patient Care | L98: 5 | M98: Intensive Care Unit | N98: =IF(M98="Cardiology","Cardio",IF(M98="Intensive Care Unit","ICU",IF(M98="Neurology","Neuro",IF(M98="Emergency Room","ER",IF(M98="Pediatrics","PD",IF(M98="Surgery","Surgery",IF(M98="General Medicine","GM",IF(M98="Orthopedics","Ortho","")))))))) -> ICU | O98: 14836.43 | P98: 8605.13 | R98: =IF(Patient_Data!$L98<2,"Low Risk",IF(Patient_Data!$L98<4,"Moderate Risk","High Risk")) -> High Risk | S98: =IF(Patient_Data[[#This Row],[Age]]<=18,"Pediatric",IF(Patient_Data[[#This Row],[Age]]<=64,"Adult","Geriatric")) -> Geriatric
A99: NHM-2023-100789 | B99: =TEXT(Patient_Data!$E99,"mmmm") -> September | C99: =LEFT(B99,3) -> Sep | D99: =MONTH(Patient_Data!$E99) -> 9 | E99: 45181 | F99: =TEXT(Patient_Data[[#This Row],[Admission_Date]],"YYYY") -> 2023 | G99: Linda Cooper | H99: NovaHealth Chicago Medical Center | I99: Female | J99: 90 | K99: In-Patient Care | L99: 4 | M99: Intensive Care Unit | N99: =IF(M99="Cardiology","Cardio",IF(M99="Intensive Care Unit","ICU",IF(M99="Neurology","Neuro",IF(M99="Emergency Room","ER",IF(M99="Pediatrics","PD",IF(M99="Surgery","Surgery",IF(M99="General Medicine","GM",IF(M99="Orthopedics","Ortho","")))))))) -> ICU | O99: 18045.56 | P99: 11146.99 | Q99: 17.4 | R99: =IF(Patient_Data!$L99<2,"Low Risk",IF(Patient_Data!$L99<4,"Moderate Risk","High Risk")) -> High Risk | S99: =IF(Patient_Data[[#This Row],[Age]]<=18,"Pediatric",IF(Patient_Data[[#This Row],[Age]]<=64,"Adult","Geriatric")) -> Geriatric
A100: NHM-2024-102113 | B100: =TEXT(Patient_Data!$E100,"mmmm") -> December | C100: =LEFT(B100,3) -> Dec | D100: =MONTH(Patient_Data!$E100) -> 12 | E100: 45287 | F100: =TEXT(Patient_Data[[#This Row],[Admission_Date]],"YYYY") -> 2023 | G100: Daniel Ford | H100: NovaHealth Northside Hospital | I100: Female | J100: 10 | K100: In-Patient Care | L100: 3 | M100: Pediatrics | N100: =IF(M100="Cardiology","Cardio",IF(M100="Intensive Care Unit","ICU",IF(M100="Neurology","Neuro",IF(M100="Emergency Room","ER",IF(M100="Pediatrics","PD",IF(M100="Surgery","Surgery",IF(M100="General Medicine","GM",IF(M100="Orthopedics","Ortho","")))))))) -> PD | O100: 3084.79 | P100: 1997.47 | Q100: 2.9 | R100: =IF(Patient_Data!$L100<2,"Low Risk",IF(Patient_Data!$L100<4,"Moderate Risk","High Risk")) -> Moderate Risk | S100: =IF(Patient_Data[[#This Row],[Age]]<=18,"Pediatric",IF(Patient_Data[[#This Row],[Age]]<=64,"Adult","Geriatric")) -> Pediatric
A101: NHM-2026-101321 | B101: =TEXT(Patient_Data!$E101,"mmmm") -> December | C101: =LEFT(B101,3) -> Dec | D101: =MONTH(Patient_Data!$E101) -> 12 | E101: 45635 | F101: =TEXT(Patient_Data[[#This Row],[Admission_Date]],"YYYY") -> 2024 | G101: Deborah Thompson | H101: NovaHealth Northside Hospital | I101: Male | J101: 57 | K101: Discharged | L101: 2 | M101: General Medicine | N101: =IF(M101="Cardiology","Cardio",IF(M101="Intensive Care Unit","ICU",IF(M101="Neurology","Neuro",IF(M101="Emergency Room","ER",IF(M101="Pediatrics","PD",IF(M101="Surgery","Surgery",IF(M101="General Medicine","GM",IF(M101="Orthopedics","Ortho","")))))))) -> GM | O101: 2639.94 | P101: 1831.96 | Q101: 7.9 | R101: =IF(Patient_Data!$L101<2,"Low Risk",IF(Patient_Data!$L101<4,"Moderate Risk","High Risk")) -> Moderate Risk | S101: =IF(Patient_Data[[#This Row],[Age]]<=18,"Pediatric",IF(Patient_Data[[#This Row],[Age]]<=64,"Adult","Geriatric")) -> Adult
A102: NHM-2025-100635 | B102: =TEXT(Patient_Data!$E102,"mmmm") -> July | C102: =LEFT(B102,3) -> Jul | D102: =MONTH(Patient_Data!$E102) -> 7 | E102: 45843 | F102: =TEXT(Patient_Data[[#This Row],[Admission_Date]],"YYYY") -> 2025 | G102: Kyle Hughes | H102: NovaHealth Greenfield Clinic | I102: Female | J102: 71 | K102: Readmitted | L102: 2 | M102: General Medicine | N102: =IF(M102="Cardiology","Cardio",IF(M102="Intensive Care Unit","ICU",IF(M102="Neurology","Neuro",IF(M102="Emergency Room","ER",IF(M102="Pediatrics","PD",IF(M102="Surgery","Surgery",IF(M102="General Medicine","GM",IF(M102="Orthopedics","Ortho","")))))))) -> GM | O102: 1892.81 | P102: 1400.97 | Q102: 9.5 | R102: =IF(Patient_Data!$L102<2,"Low Risk",IF(Patient_Data!$L102<4,"Moderate Risk","High Risk")) -> Moderate Risk | S102: =IF(Patient_Data[[#This Row],[Age]]<=18,"Pediatric",IF(Patient_Data[[#This Row],[Age]]<=64,"Adult","Geriatric")) -> Geriatric
A103: NHM-2023-100382 | B103: =TEXT(Patient_Data!$E103,"mmmm") -> May | C103: =LEFT(B103,3) -> May | D103: =MONTH(Patient_Data!$E103) -> 5 | E103: 46161 | F103: =TEXT(Patient_Data[[#This Row],[Admission_Date]],"YYYY") -> 2026 | G103: Brandon Martinez | H103: NovaHealth Greenfield Clinic | I103: Female | J103: 57 | K103: Readmitted | L103: 4 | M103: Surgery | N103: =IF(M103="Cardiology","Cardio",IF(M103="Intensive Care Unit","ICU",IF(M103="Neurology","Neuro",IF(M103="Emergency Room","ER",IF(M103="Pediatrics","PD",IF(M103="Surgery","Surgery",IF(M103="General Medicine","GM",IF(M103="Orthopedics","Ortho","")))))))) -> Surgery | O103: 18363.29 | P103: 13454 | Q103: 6.1 | R103: =IF(Patient_Data!$L103<2,"Low Risk",IF(Patient_Data!$L103<4,"Moderate Risk","High Risk")) -> High Risk | S103: =IF(Patient_Data[[#This Row],[Age]]<=18,"Pediatric",IF(Patient_Data[[#This Row],[Age]]<=64,"Adult","Geriatric")) -> Adult
A104: NHM-2026-101549 | B104: =TEXT(Patient_Data!$E104,"mmmm") -> April | C104: =LEFT(B104,3) -> Apr | D104: =MONTH(Patient_Data!$E104) -> 4 | E104: 46135 | F104: =TEXT(Patient_Data[[#This Row],[Admission_Date]],"YYYY") -> 2026 | G104: Rachel Marshall | H104: NovaHealth Greenfield Clinic | I104: Female | J104: 79 | K104: Discharged | L104: 3 | M104: Neurology | N104: =IF(M104="Cardiology","Cardio",IF(M104="Intensive Care Unit","ICU",IF(M104="Neurology","Neuro",IF(M104="Emergency Room","ER",IF(M104="Pediatrics","PD",IF(M104="Surgery","Surgery",IF(M104="General Medicine","GM",IF(M104="Orthopedics","Ortho","")))))))) -> Neuro | O104: 10144.1 | P104: 7798.32 | Q104: 11.1 | R104: =IF(Patient_Data!$L104<2,"Low Risk",IF(Patient_Data!$L104<4,"Moderate Risk","High Risk")) -> Moderate Risk | S104: =IF(Patient_Data[[#This Row],[Age]]<=18,"Pediatric",IF(Patient_Data[[#This Row],[Age]]<=64,"Adult","Geriatric")) -> Geriatric
A105: NHM-2025-102422 | B105: =TEXT(Patient_Data!$E105,"mmmm") -> January | C105: =LEFT(B105,3) -> Jan | D105: =MONTH(Patient_Data!$E105) -> 1 | E105: 45664 | F105: =TEXT(Patient_Data[[#This Row],[Admission_Date]],"YYYY") -> 2025 | G105: Diane Reynolds | H105: NovaHealth Northside Hospital | I105: Female | J105: 72 | K105: Readmitted | L105: 5 | M105: Intensive Care Unit | N105: =IF(M105="Cardiology","Cardio",IF(M105="Intensive Care Unit","ICU",IF(M105="Neurology","Neuro",IF(M105="Emergency Room","ER",IF(M105="Pediatrics","PD",IF(M105="Surgery","Surgery",IF(M105="General Medicine","GM",IF(M105="Orthopedics","Ortho","")))))))) -> ICU | O105: 11452.59 | P105: 6769.7 | Q105: 15.9 | R105: =IF(Patient_Data!$L105<2,"Low Risk",IF(Patient_Data!$L105<4,"Moderate Risk","High Risk")) -> High Risk | S105: =IF(Patient_Data[[#This Row],[Age]]<=18,"Pediatric",IF(Patient_Data[[#This Row],[Age]]<=64,"Adult","Geriatric")) -> Geriatric
A106: NHM-2023-101918 | B106: =TEXT(Patient_Data!$E106,"mmmm") -> April | C106: =LEFT(B106,3) -> Apr | D106: =MONTH(Patient_Data!$E106) -> 4 | E106: 46135 | F106: =TEXT(Patient_Data[[#This Row],[Admission_Date]],"YYYY") -> 2026 | G106: Joe Myers | H106: NovaHealth Chicago Medical Center | I106: Female | J106: 80 | K106: In-Patient Care | L106: 4 | M106: Cardiology | N106: =IF(M106="Cardiology","Cardio",IF(M106="Intensive Care Unit","ICU",IF(M106="Neurology","Neuro",IF(M106="Emergency Room","ER",IF(M106="Pediatrics","PD",IF(M106="Surgery","Surgery",IF(M106="General Medicine","GM",IF(M106="Orthopedics","Ortho","")))))))) -> Cardio | O106: 8820.6 | P106: 5449.37 | Q106: 8.6 | R106: =IF(Patient_Data!$L106<2,"Low Risk",IF(Patient_Data!$L106<4,"Moderate Risk","High Risk")) -> High Risk | S106: =IF(Patient_Data[[#This Row],[Age]]<=18,"Pediatric",IF(Patient_Data[[#This Row],[Age]]<=64,"Adult","Geriatric")) -> Geriatric
A107: NHM-2024-102496 | B107: =TEXT(Patient_Data!$E107,"mmmm") -> December | C107: =LEFT(B107,3) -> Dec | D107: =MONTH(Patient_Data!$E107) -> 12 | E107: 46000 | F107: =TEXT(Patient_Data[[#This Row],[Admission_Date]],"YYYY") -> 2025 | G107: James Jenkins | H107: NovaHealth Midtown Medical Center | I107: Male | J107: 29 | K107: Discharged | L107: 1 | M107: Neurology | N107: =IF(M107="Cardiology","Cardio",IF(M107="Intensive Care Unit","ICU",IF(M107="Neurology","Neuro",IF(M107="Emergency Room","ER",IF(M107="Pediatrics","PD",IF(M107="Surgery","Surgery",IF(M107="General Medicine","GM",IF(M107="Orthopedics","Ortho","")))))))) -> Neuro | O107: 5500.22 | P107: 3552.94 | Q107: 4.1 | R107: =IF(Patient_Data!$L107<2,"Low Risk",IF(Patient_Data!$L107<4,"Moderate Risk","High Risk")) -> Low Risk | S107: =IF(Patient_Data[[#This Row],[Age]]<=18,"Pediatric",IF(Patient_Data[[#This Row],[Age]]<=64,"Adult","Geriatric")) -> Adult
A108: NHM-2024-102468 | B108: =TEXT(Patient_Data!$E108,"mmmm") -> September | C108: =LEFT(B108,3) -> Sep | D108: =MONTH(Patient_Data!$E108) -> 9 | E108: 45556 | F108: =TEXT(Patient_Data[[#This Row],[Admission_Date]],"YYYY") -> 2024 | G108: Ralph Miller | H108: NovaHealth Chicago Medical Center | I108: Female | J108: 90 | K108: In-Patient Care | L108: 4 | M108: Intensive Care Unit | N108: =IF(M108="Cardiology","Cardio",IF(M108="Intensive Care Unit","ICU",IF(M108="Neurology","Neuro",IF(M108="Emergency Room","ER",IF(M108="Pediatrics","PD",IF(M108="Surgery","Surgery",IF(M108="General Medicine","GM",IF(M108="Orthopedics","Ortho","")))))))) -> ICU | O108: 11284.32 | P108: 7560.49 | R108: =IF(Patient_Data!$L108<2,"Low Risk",IF(Patient_Data!$L108<4,"Moderate Risk","High Risk")) -> High Risk | S108: =IF(Patient_Data[[#This Row],[Age]]<=18,"Pediatric",IF(Patient_Data[[#This Row],[Age]]<=64,"Adult","Geriatric")) -> Geriatric
A109: NHM-2025-100756 | B109: =TEXT(Patient_Data!$E109,"mmmm") -> January | C109: =LEFT(B109,3) -> Jan | D109: =MONTH(Patient_Data!$E109) -> 1 | E109: 46049 | F109: =TEXT(Patient_Data[[#This Row],[Admission_Date]],"YYYY") -> 2026 | G109: Bruce Diaz | H109: NovaHealth Chicago Medical Center | I109: Female | J109: 52 | K109: Discharged | L109: 1 | M109: Orthopedics | N109: =IF(M109="Cardiology","Cardio",IF(M109="Intensive Care Unit","ICU",IF(M109="Neurology","Neuro",IF(M109="Emergency Room","ER",IF(M109="Pediatrics","PD",IF(M109="Surgery","Surgery",IF(M109="General Medicine","GM",IF(M109="Orthopedics","Ortho","")))))))) -> Ortho | O109: 7849.84 | P109: 5561.29 | Q109: 8.3 | R109: =IF(Patient_Data!$L109<2,"Low Risk",IF(Patient_Data!$L109<4,"Moderate Risk","High Risk")) -> Low Risk | S109: =IF(Patient_Data[[#This Row],[Age]]<=18,"Pediatric",IF(Patient_Data[[#This Row],[Age]]<=64,"Adult","Geriatric")) -> Adult
A110: NHM-2024-100952 | B110: =TEXT(Patient_Data!$E110,"mmmm") -> March | C110: =LEFT(B110,3) -> Mar | D110: =MONTH(Patient_Data!$E110) -> 3 | E110: 45368 | F110: =TEXT(Patient_Data[[#This Row],[Admission_Date]],"YYYY") -> 2024 | G110: Grace Alexander | H110: NovaHealth Northside Hospital | I110: Male | J110: 32 | K110: In-Patient Care | L110: 4 | M110: Surgery | N110: =IF(M110="Cardiology","Cardio",IF(M110="Intensive Care Unit","ICU",IF(M110="Neurology","Neuro",IF(M110="Emergency Room","ER",IF(M110="Pediatrics","PD",IF(M110="Surgery","Surgery",IF(M110="General Medicine","GM",IF(M110="Orthopedics","Ortho","")))))))) -> Surgery | O110: 22910.18 | P110: 16755.63 | Q110: 3.9 | R110: =IF(Patient_Data!$L110<2,"Low Risk",IF(Patient_Data!$L110<4,"Moderate Risk","High Risk")) -> High Risk | S110: =IF(Patient_Data[[#This Row],[Age]]<=18,"Pediatric",IF(Patient_Data[[#This Row],[Age]]<=64,"Adult","Geriatric")) -> Adult
A111: NHM-2023-101702 | B111: =TEXT(Patient_Data!$E111,"mmmm") -> July | C111: =LEFT(B111,3) -> Jul | D111: =MONTH(Patient_Data!$E111) -> 7 | E111: 45861 | F111: =TEXT(Patient_Data[[#This Row],[Admission_Date]],"YYYY") -> 2025 | G111: Juan Patel | H111: NovaHealth Lakeside Medical Center | I111: Male | J111: 80 | K111: Readmitted | L111: 3 | M111: Surgery | N111: =IF(M111="Cardiology","Cardio",IF(M111="Intensive Care Unit","ICU",IF(M111="Neurology","Neuro",IF(M111="Emergency Room","ER",IF(M111="Pediatrics","PD",IF(M111="Surgery","Surgery",IF(M111="General Medicine","GM",IF(M111="Orthopedics","Ortho","")))))))) -> Surgery | O111: 14981.93 | P111: 11468.67 | Q111: 10.3 | R111: =IF(Patient_Data!$L111<2,"Low Risk",IF(Patient_Data!$L111<4,"Moderate Risk","High Risk")) -> Moderate Risk | S111: =IF(Patient_Data[[#This Row],[Age]]<=18,"Pediatric",IF(Patient_Data[[#This Row],[Age]]<=64,"Adult","Geriatric")) -> Geriatric
A112: NHM-2023-101430 | B112: =TEXT(Patient_Data!$E112,"mmmm") -> April | C112: =LEFT(B112,3) -> Apr | D112: =MONTH(Patient_Data!$E112) -> 4 | E112: 45390 | F112: =TEXT(Patient_Data[[#This Row],[Admission_Date]],"YYYY") -> 2024 | G112: Edward Coleman | H112: NovaHealth Metro General Hospital | I112: Female | J112: 81 | K112: In-Patient Care | L112: 4 | M112: Intensive Care Unit | N112: =IF(M112="Cardiology","Cardio",IF(M112="Intensive Care Unit","ICU",IF(M112="Neurology","Neuro",IF(M112="Emergency Room","ER",IF(M112="Pediatrics","PD",IF(M112="Surgery","Surgery",IF(M112="General Medicine","GM",IF(M112="Orthopedics","Ortho","")))))))) -> ICU | O112: 13603.14 | P112: 7961.02 | Q112: 8.9 | R112: =IF(Patient_Data!$L112<2,"Low Risk",IF(Patient_Data!$L112<4,"Moderate Risk","High Risk")) -> High Risk | S112: =IF(Patient_Data[[#This Row],[Age]]<=18,"Pediatric",IF(Patient_Data[[#This Row],[Age]]<=64,"Adult","Geriatric")) -> Geriatric
A113: NHM-2023-100623 | B113: =TEXT(Patient_Data!$E113,"mmmm") -> March | C113: =LEFT(B113,3) -> Mar | D113: =MONTH(Patient_Data!$E113) -> 3 | E113: 46085 | F113: =TEXT(Patient_Data[[#This Row],[Admission_Date]],"YYYY") -> 2026 | G113: Janice Crawford | H113: NovaHealth Chicago Medical Center | I113: Female | J113: 95 | K113: Discharged | L113: 4 | M113: Orthopedics | N113: =IF(M113="Cardiology","Cardio",IF(M113="Intensive Care Unit","ICU",IF(M113="Neurology","Neuro",IF(M113="Emergency Room","ER",IF(M113="Pediatrics","PD",IF(M113="Surgery","Surgery",IF(M113="General Medicine","GM",IF(M113="Orthopedics","Ortho","")))))))) -> Ortho | O113: 10262.95 | P113: 6300.4 | Q113: 5 | R113: =IF(Patient_Data!$L113<2,"Low Risk",IF(Patient_Data!$L113<4,"Moderate Risk","High Risk")) -> High Risk | S113: =IF(Patient_Data[[#This Row],[Age]]<=18,"Pediatric",IF(Patient_Data[[#This Row],[Age]]<=64,"Adult","Geriatric")) -> Geriatric
A114: NHM-2024-101884 | B114: =TEXT(Patient_Data!$E114,"mmmm") -> June | C114: =LEFT(B114,3) -> Jun | D114: =MONTH(Patient_Data!$E114) -> 6 | E114: 45454 | F114: =TEXT(Patient_Data[[#This Row],[Admission_Date]],"YYYY") -> 2024 | G114: Beverly Stevens | H114: NovaHealth River Valley Hospital | I114: Female | J114: 68 | K114: Discharged | L114: 1 | M114: Emergency Room | N114: =IF(M114="Cardiology","Cardio",IF(M114="Intensive Care Unit","ICU",IF(M114="Neurology","Neuro",IF(M114="Emergency Room","ER",IF(M114="Pediatrics","PD",IF(M114="Surgery","Surgery",IF(M114="General Medicine","GM",IF(M114="Orthopedics","Ortho","")))))))) -> ER | O114: 3646.44 | P114: 2456.92 | Q114: 15.4 | R114: =IF(Patient_Data!$L114<2,"Low Risk",IF(Patient_Data!$L114<4,"Moderate Risk","High Risk")) -> Low Risk | S114: =IF(Patient_Data[[#This Row],[Age]]<=18,"Pediatric",IF(Patient_Data[[#This Row],[Age]]<=64,"Adult","Geriatric")) -> Geriatric
A115: NHM-2024-100230 | B115: =TEXT(Patient_Data!$E115,"mmmm") -> January | C115: =LEFT(B115,3) -> Jan | D115: =MONTH(Patient_Data!$E115) -> 1 | E115: 46031 | F115: =TEXT(Patient_Data[[#This Row],[Admission_Date]],"YYYY") -> 2026 | G115: Catherine Russell | H115: NovaHealth Lakeside Medical Center | I115: Female | J115: 66 | K115: Readmitted | L115: 3 | M115: Emergency Room | N115: =IF(M115="Cardiology","Cardio",IF(M115="Intensive Care Unit","ICU",IF(M115="Neurology","Neuro",IF(M115="Emergency Room","ER",IF(M115="Pediatrics","PD",IF(M115="Surgery","Surgery",IF(M115="General Medicine","GM",IF(M115="Orthopedics","Ortho","")))))))) -> ER | O115: 6590.34 | P115: 4585.13 | Q115: 21.2 | R115: =IF(Patient_Data!$L115<2,"Low Risk",IF(Patient_Data!$L115<4,"Moderate Risk","High Risk")) -> Moderate Risk | S115: =IF(Patient_Data[[#This Row],[Age]]<=18,"Pediatric",IF(Patient_Data[[#This Row],[Age]]<=64,"Adult","Geriatric")) -> Geriatric
A116: NHM-2025-100947 | B116: =TEXT(Patient_Data!$E116,"mmmm") -> January | C116: =LEFT(B116,3) -> Jan | D116: =MONTH(Patient_Data!$E116) -> 1 | E116: 45678 | F116: =TEXT(Patient_Data[[#This Row],[Admission_Date]],"YYYY") -> 2025 | G116: Martha Hughes | H116: NovaHealth Chicago Medical Center | I116: Male | J116: 63 | K116: Discharged | L116: 2 | M116: General Medicine | N116: =IF(M116="Cardiology","Cardio",IF(M116="Intensive Care Unit","ICU",IF(M116="Neurology","Neuro",IF(M116="Emergency Room","ER",IF(M116="Pediatrics","PD",IF(M116="Surgery","Surgery",IF(M116="General Medicine","GM",IF(M116="Orthopedics","Ortho","")))))))) -> GM | O116: 3062.14 | P116: 2198.7 | Q116: 6.9 | R116: =IF(Patient_Data!$L116<2,"Low Risk",IF(Patient_Data!$L116<4,"Moderate Risk","High Risk")) -> Moderate Risk | S116: =IF(Patient_Data[[#This Row],[Age]]<=18,"Pediatric",IF(Patient_Data[[#This Row],[Age]]<=64,"Adult","Geriatric")) -> Adult
A117: NHM-2024-101222 | B117: =TEXT(Patient_Data!$E117,"mmmm") -> January | C117: =LEFT(B117,3) -> Jan | D117: =MONTH(Patient_Data!$E117) -> 1 | E117: 45321 | F117: =TEXT(Patient_Data[[#This Row],[Admission_Date]],"YYYY") -> 2024 | G117: Noah Murray | H117: NovaHealth Greenfield Clinic | I117: Male | J117: 69 | K117: Readmitted | L117: 4 | M117: Orthopedics | N117: =IF(M117="Cardiology","Cardio",IF(M117="Intensive Care Unit","ICU",IF(M117="Neurology","Neuro",IF(M117="Emergency Room","ER",IF(M117="Pediatrics","PD",IF(M117="Surgery","Surgery",IF(M117="General Medicine","GM",IF(M117="Orthopedics","Ortho","")))))))) -> Ortho | O117: 13290.19 | P117: 9775.44 | Q117: 9.2 | R117: =IF(Patient_Data!$L117<2,"Low Risk",IF(Patient_Data!$L117<4,"Moderate Risk","High Risk")) -> High Risk | S117: =IF(Patient_Data[[#This Row],[Age]]<=18,"Pediatric",IF(Patient_Data[[#This Row],[Age]]<=64,"Adult","Geriatric")) -> Geriatric
A118: NHM-2024-100850 | B118: =TEXT(Patient_Data!$E118,"mmmm") -> March | C118: =LEFT(B118,3) -> Mar | D118: =MONTH(Patient_Data!$E118) -> 3 | E118: 45367 | F118: =TEXT(Patient_Data[[#This Row],[Admission_Date]],"YYYY") -> 2024 | G118: Justin Morris | H118: NovaHealth Greenfield Clinic | I118: Female | J118: 70 | K118: Discharged | L118: 3 | M118: General Medicine | N118: =IF(M118="Cardiology","Cardio",IF(M118="Intensive Care Unit","ICU",IF(M118="Neurology","Neuro",IF(M118="Emergency Room","ER",IF(M118="Pediatrics","PD",IF(M118="Surgery","Surgery",IF(M118="General Medicine","GM",IF(M118="Orthopedics","Ortho","")))))))) -> GM | O118: 4408.36 | P118: 3423.15 | Q118: 9.1 | R118: =IF(Patient_Data!$L118<2,"Low Risk",IF(Patient_Data!$L118<4,"Moderate Risk","High Risk")) -> Moderate Risk | S118: =IF(Patient_Data[[#This Row],[Age]]<=18,"Pediatric",IF(Patient_Data[[#This Row],[Age]]<=64,"Adult","Geriatric")) -> Geriatric
A119: NHM-2023-101928 | B119: =TEXT(Patient_Data!$E119,"mmmm") -> September | C119: =LEFT(B119,3) -> Sep | D119: =MONTH(Patient_Data!$E119) -> 9 | E119: 45197 | F119: =TEXT(Patient_Data[[#This Row],[Admission_Date]],"YYYY") -> 2023 | G119: Sandra Ortiz | H119: NovaHealth River Valley Hospital | I119: Female | J119: 52 | K119: Discharged | L119: 3 | M119: Cardiology | N119: =IF(M119="Cardiology","Cardio",IF(M119="Intensive Care Unit","ICU",IF(M119="Neurology","Neuro",IF(M119="Emergency Room","ER",IF(M119="Pediatrics","PD",IF(M119="Surgery","Surgery",IF(M119="General Medicine","GM",IF(M119="Orthopedics","Ortho","")))))))) -> Cardio | O119: 14505.45 | P119: 8445.96 | Q119: 4.1 | R119: =IF(Patient_Data!$L119<2,"Low Risk",IF(Patient_Data!$L119<4,"Moderate Risk","High Risk")) -> Moderate Risk | S119: =IF(Patient_Data[[#This Row],[Age]]<=18,"Pediatric",IF(Patient_Data[[#This Row],[Age]]<=64,"Adult","Geriatric")) -> Adult
A120: NHM-2023-101259 | B120: =TEXT(Patient_Data!$E120,"mmmm") -> March | C120: =LEFT(B120,3) -> Mar | D120: =MONTH(Patient_Data!$E120) -> 3 | E120: 45358 | F120: =TEXT(Patient_Data[[#This Row],[Admission_Date]],"YYYY") -> 2024 | G120: Juan Lewis | H120: NovaHealth Chicago Medical Center | I120: Female | J120: 58 | K120: Discharged | L120: 1 | M120: Orthopedics | N120: =IF(M120="Cardiology","Cardio",IF(M120="Intensive Care Unit","ICU",IF(M120="Neurology","Neuro",IF(M120="Emergency Room","ER",IF(M120="Pediatrics","PD",IF(M120="Surgery","Surgery",IF(M120="General Medicine","GM",IF(M120="Orthopedics","Ortho","")))))))) -> Ortho | O120: 4112.98 | P120: 2565.72 | Q120: 7.1 | R120: =IF(Patient_Data!$L120<2,"Low Risk",IF(Patient_Data!$L120<4,"Moderate Risk","High Risk")) -> Low Risk | S120: =IF(Patient_Data[[#This Row],[Age]]<=18,"Pediatric",IF(Patient_Data[[#This Row],[Age]]<=64,"Adult","Geriatric")) -> Adult
... A173: NHM-2024-101413 | B173: =TEXT(Patient_Data!$E173,"mmmm") -> November | C173: =LEFT(B173,3) -> Nov | D173: =MONTH(Patient_Data!$E173) -> 11 | E173: 45257 | F173: =TEXT(Patient_Data[[#This Row],[Admission_Date]],"YYYY") -> 2023 | G173: Sean Robinson | H173: NovaHealth Metro General Hospital | I173: Female | J173: 80 | K173: In-Patient Care | L173: 4 | M173: Neurology | N173: =IF(M173="Cardiology","Cardio",IF(M173="Intensive Care Unit","ICU",IF(M173="Neurology","Neuro",IF(M173="Emergency Room","ER",IF(M173="Pediatrics","PD",IF(M173="Surgery","Surgery",IF(M173="General Medicine","GM",IF(M173="Orthopedics","Ortho","")))))))) -> Neuro | O173: 13840.27 | P173: 10169 | Q173: 8.2 | R173: =IF(Patient_Data!$L173<2,"Low Risk",IF(Patient_Data!$L173<4,"Moderate Risk","High Risk")) -> High Risk | S173: =IF(Patient_Data[[#This Row],[Age]]<=18,"Pediatric",IF(Patient_Data[[#This Row],[Age]]<=64,"Adult","Geriatric")) -> Geriatric
A174: NHM-2023-100429 | B174: =TEXT(Patient_Data!$E174,"mmmm") -> September | C174: =LEFT(B174,3) -> Sep | D174: =MONTH(Patient_Data!$E174) -> 9 | E174: 45174 | F174: =TEXT(Patient_Data[[#This Row],[Admission_Date]],"YYYY") -> 2023 | G174: Jason Stevens | H174: NovaHealth Greenfield Clinic | I174: Female | J174: 61 | K174: Discharged | L174: 1 | M174: Cardiology | N174: =IF(M174="Cardiology","Cardio",IF(M174="Intensive Care Unit","ICU",IF(M174="Neurology","Neuro",IF(M174="Emergency Room","ER",IF(M174="Pediatrics","PD",IF(M174="Surgery","Surgery",IF(M174="General Medicine","GM",IF(M174="Orthopedics","Ortho","")))))))) -> Cardio | O174: 8675.78 | P174: 6593.59 | R174: =IF(Patient_Data!$L174<2,"Low Risk",IF(Patient_Data!$L174<4,"Moderate Risk","High Risk")) -> Low Risk | S174: =IF(Patient_Data[[#This Row],[Age]]<=18,"Pediatric",IF(Patient_Data[[#This Row],[Age]]<=64,"Adult","Geriatric")) -> Adult
A175: NHM-2023-102183 | B175: =TEXT(Patient_Data!$E175,"mmmm") -> February | C175: =LEFT(B175,3) -> Feb | D175: =MONTH(Patient_Data!$E175) -> 2 | E175: 46071 | F175: =TEXT(Patient_Data[[#This Row],[Admission_Date]],"YYYY") -> 2026 | G175: Kathleen Reyes | H175: NovaHealth Chicago Medical Center | I175: Female | J175: 28 | K175: Discharged | L175: 3 | M175: Surgery | N175: =IF(M175="Cardiology","Cardio",IF(M175="Intensive Care Unit","ICU",IF(M175="Neurology","Neuro",IF(M175="Emergency Room","ER",IF(M175="Pediatrics","PD",IF(M175="Surgery","Surgery",IF(M175="General Medicine","GM",IF(M175="Orthopedics","Ortho","")))))))) -> Surgery | O175: 11532.68 | P175: 6772.95 | Q175: 10.5 | R175: =IF(Patient_Data!$L175<2,"Low Risk",IF(Patient_Data!$L175<4,"Moderate Risk","High Risk")) -> Moderate Risk | S175: =IF(Patient_Data[[#This Row],[Age]]<=18,"Pediatric",IF(Patient_Data[[#This Row],[Age]]<=64,"Adult","Geriatric")) -> Adult
A176: NHM-2025-101619 | B176: =TEXT(Patient_Data!$E176,"mmmm") -> January | C176: =LEFT(B176,3) -> Jan | D176: =MONTH(Patient_Data!$E176) -> 1 | E176: 46042 | F176: =TEXT(Patient_Data[[#This Row],[Admission_Date]],"YYYY") -> 2026 | G176: Benjamin Graham | H176: NovaHealth Midtown Medical Center | I176: Female | J176: 37 | K176: Discharged | L176: 4 | M176: Surgery | N176: =IF(M176="Cardiology","Cardio",IF(M176="Intensive Care Unit","ICU",IF(M176="Neurology","Neuro",IF(M176="Emergency Room","ER",IF(M176="Pediatrics","PD",IF(M176="Surgery","Surgery",IF(M176="General Medicine","GM",IF(M176="Orthopedics","Ortho","")))))))) -> Surgery | O176: 20902.73 | P176: 12783.47 | Q176: 4.1 | R176: =IF(Patient_Data!$L176<2,"Low Risk",IF(Patient_Data!$L176<4,"Moderate Risk","High Risk")) -> High Risk | S176: =IF(Patient_Data[[#This Row],[Age]]<=18,"Pediatric",IF(Patient_Data[[#This Row],[Age]]<=64,"Adult","Geriatric")) -> Adult
A177: NHM-2023-101974 | B177: =TEXT(Patient_Data!$E177,"mmmm") -> September | C177: =LEFT(B177,3) -> Sep | D177: =MONTH(Patient_Data!$E177) -> 9 | E177: 45186 | F177: =TEXT(Patient_Data[[#This Row],[Admission_Date]],"YYYY") -> 2023 | G177: Gregory Foster | H177: NovaHealth Greenfield Clinic | I177: Female | J177: 17 | K177: Discharged | L177: 2 | M177: Pediatrics | N177: =IF(M177="Cardiology","Cardio",IF(M177="Intensive Care Unit","ICU",IF(M177="Neurology","Neuro",IF(M177="Emergency Room","ER",IF(M177="Pediatrics","PD",IF(M177="Surgery","Surgery",IF(M177="General Medicine","GM",IF(M177="Orthopedics","Ortho","")))))))) -> PD | O177: 2943.48 | P177: 1885.43 | Q177: 0.2 | R177: =IF(Patient_Data!$L177<2,"Low Risk",IF(Patient_Data!$L177<4,"Moderate Risk","High Risk")) -> Moderate Risk | S177: =IF(Patient_Data[[#This Row],[Age]]<=18,"Pediatric",IF(Patient_Data[[#This Row],[Age]]<=64,"Adult","Geriatric")) -> Pediatric
A178: NHM-2026-100198 | B178: =TEXT(Patient_Data!$E178,"mmmm") -> September | C178: =LEFT(B178,3) -> Sep | D178: =MONTH(Patient_Data!$E178) -> 9 | E178: 45923 | F178: =TEXT(Patient_Data[[#This Row],[Admission_Date]],"YYYY") -> 2025 | G178: Tyler Richardson | H178: NovaHealth Metro General Hospital | I178: Female | J178: 70 | K178: In-Patient Care | L178: 5 | M178: Intensive Care Unit | N178: =IF(M178="Cardiology","Cardio",IF(M178="Intensive Care Unit","ICU",IF(M178="Neurology","Neuro",IF(M178="Emergency Room","ER",IF(M178="Pediatrics","PD",IF(M178="Surgery","Surgery",IF(M178="General Medicine","GM",IF(M178="Orthopedics","Ortho","")))))))) -> ICU | O178: 18292.35 | P178: 12372.67 | Q178: 14.6 | R178: =IF(Patient_Data!$L178<2,"Low Risk",IF(Patient_Data!$L178<4,"Moderate Risk","High Risk")) -> High Risk | S178: =IF(Patient_Data[[#This Row],[Age]]<=18,"Pediatric",IF(Patient_Data[[#This Row],[Age]]<=64,"Adult","Geriatric")) -> Geriatric
A179: NHM-2024-100907 | B179: =TEXT(Patient_Data!$E179,"mmmm") -> June | C179: =LEFT(B179,3) -> Jun | D179: =MONTH(Patient_Data!$E179) -> 6 | E179: 45470 | F179: =TEXT(Patient_Data[[#This Row],[Admission_Date]],"YYYY") -> 2024 | G179: Nathan Stevens | H179: NovaHealth Chicago Medical Center | I179: Female | J179: 24 | K179: Discharged | L179: 2 | M179: Emergency Room | N179: =IF(M179="Cardiology","Cardio",IF(M179="Intensive Care Unit","ICU",IF(M179="Neurology","Neuro",IF(M179="Emergency Room","ER",IF(M179="Pediatrics","PD",IF(M179="Surgery","Surgery",IF(M179="General Medicine","GM",IF(M179="Orthopedics","Ortho","")))))))) -> ER | O179: 8884.35 | P179: 6323.85 | Q179: 13.1 | R179: =IF(Patient_Data!$L179<2,"Low Risk",IF(Patient_Data!$L179<4,"Moderate Risk","High Risk")) -> Moderate Risk | S179: =IF(Patient_Data[[#This Row],[Age]]<=18,"Pediatric",IF(Patient_Data[[#This Row],[Age]]<=64,"Adult","Geriatric")) -> Adult
A180: NHM-2026-102316 | B180: =TEXT(Patient_Data!$E180,"mmmm") -> January | C180: =LEFT(B180,3) -> Jan | D180: =MONTH(Patient_Data!$E180) -> 1 | E180: 46047 | F180: =TEXT(Patient_Data[[#This Row],[Admission_Date]],"YYYY") -> 2026 | G180: Donna Hamilton | H180: NovaHealth River Valley Hospital | I180: Male | J180: 80 | K180: Discharged | L180: 2 | M180: Orthopedics | N180: =IF(M180="Cardiology","Cardio",IF(M180="Intensive Care Unit","ICU",IF(M180="Neurology","Neuro",IF(M180="Emergency Room","ER",IF(M180="Pediatrics","PD",IF(M180="Surgery","Surgery",IF(M180="General Medicine","GM",IF(M180="Orthopedics","Ortho","")))))))) -> Ortho | O180: 7381.44 | P180: 5406.85 | Q180: 2.3 | R180: =IF(Patient_Data!$L180<2,"Low Risk",IF(Patient_Data!$L180<4,"Moderate Risk","High Risk")) -> Moderate Risk | S180: =IF(Patient_Data[[#This Row],[Age]]<=18,"Pediatric",IF(Patient_Data[[#This Row],[Age]]<=64,"Adult","Geriatric")) -> Geriatric
A181: NHM-2023-102159 | B181: =TEXT(Patient_Data!$E181,"mmmm") -> May | C181: =LEFT(B181,3) -> May | D181: =MONTH(Patient_Data!$E181) -> 5 | E181: 45798 | F181: =TEXT(Patient_Data[[#This Row],[Admission_Date]],"YYYY") -> 2025 | G181: Jeremy Diaz | H181: NovaHealth Greenfield Clinic | I181: Male | J181: 48 | K181: In-Patient Care | L181: 3 | M181: Neurology | N181: =IF(M181="Cardiology","Cardio",IF(M181="Intensive Care Unit","ICU",IF(M181="Neurology","Neuro",IF(M181="Emergency Room","ER",IF(M181="Pediatrics","PD",IF(M181="Surgery","Surgery",IF(M181="General Medicine","GM",IF(M181="Orthopedics","Ortho","")))))))) -> Neuro | O181: 10694.18 | P181: 8194.78 | Q181: 8.4 | R181: =IF(Patient_Data!$L181<2,"Low Risk",IF(Patient_Data!$L181<4,"Moderate Risk","High Risk")) -> Moderate Risk | S181: =IF(Patient_Data[[#This Row],[Age]]<=18,"Pediatric",IF(Patient_Data[[#This Row],[Age]]<=64,"Adult","Geriatric")) -> Adult
A182: NHM-2026-100547 | B182: =TEXT(Patient_Data!$E182,"mmmm") -> November | C182: =LEFT(B182,3) -> Nov | D182: =MONTH(Patient_Data!$E182) -> 11 | E182: 45597 | F182: =TEXT(Patient_Data[[#This Row],[Admission_Date]],"YYYY") -> 2024 | G182: Jeffrey Mcdonald | H182: NovaHealth Lakeshore Regional Center | I182: Female | J182: 24 | K182: Discharged | L182: 1 | M182: Cardiology | N182: =IF(M182="Cardiology","Cardio",IF(M182="Intensive Care Unit","ICU",IF(M182="Neurology","Neuro",IF(M182="Emergency Room","ER",IF(M182="Pediatrics","PD",IF(M182="Surgery","Surgery",IF(M182="General Medicine","GM",IF(M182="Orthopedics","Ortho","")))))))) -> Cardio | O182: 7809.93 | P182: 4602.56 | Q182: 9.1 | R182: =IF(Patient_Data!$L182<2,"Low Risk",IF(Patient_Data!$L182<4,"Moderate Risk","High Risk")) -> Low Risk | S182: =IF(Patient_Data[[#This Row],[Age]]<=18,"Pediatric",IF(Patient_Data[[#This Row],[Age]]<=64,"Adult","Geriatric")) -> Adult
A183: NHM-2025-101957 | B183: =TEXT(Patient_Data!$E183,"mmmm") -> January | C183: =LEFT(B183,3) -> Jan | D183: =MONTH(Patient_Data!$E183) -> 1 | E183: 45678 | F183: =TEXT(Patient_Data[[#This Row],[Admission_Date]],"YYYY") -> 2025 | G183: Kelly Watson | H183: NovaHealth Metro General Hospital | I183: Male | J183: 28 | K183: Discharged | L183: 3 | M183: General Medicine | N183: =IF(M183="Cardiology","Cardio",IF(M183="Intensive Care Unit","ICU",IF(M183="Neurology","Neuro",IF(M183="Emergency Room","ER",IF(M183="Pediatrics","PD",IF(M183="Surgery","Surgery",IF(M183="General Medicine","GM",IF(M183="Orthopedics","Ortho","")))))))) -> GM | O183: 2663.22 | P183: 1682.96 | Q183: 7.3 | R183: =IF(Patient_Data!$L183<2,"Low Risk",IF(Patient_Data!$L183<4,"Moderate Risk","High Risk")) -> Moderate Risk | S183: =IF(Patient_Data[[#This Row],[Age]]<=18,"Pediatric",IF(Patient_Data[[#This Row],[Age]]<=64,"Adult","Geriatric")) -> Adult
A184: NHM-2023-100846 | B184: =TEXT(Patient_Data!$E184,"mmmm") -> March | C184: =LEFT(B184,3) -> Mar | D184: =MONTH(Patient_Data!$E184) -> 3 | E184: 45377 | F184: =TEXT(Patient_Data[[#This Row],[Admission_Date]],"YYYY") -> 2024 | G184: Logan Tucker | H184: NovaHealth Midtown Medical Center | I184: Female | J184: 29 | K184: Discharged | L184: 2 | M184: Neurology | N184: =IF(M184="Cardiology","Cardio",IF(M184="Intensive Care Unit","ICU",IF(M184="Neurology","Neuro",IF(M184="Emergency Room","ER",IF(M184="Pediatrics","PD",IF(M184="Surgery","Surgery",IF(M184="General Medicine","GM",IF(M184="Orthopedics","Ortho","")))))))) -> Neuro | O184: 10576.29 | P184: 6790.43 | Q184: 2.7 | R184: =IF(Patient_Data!$L184<2,"Low Risk",IF(Patient_Data!$L184<4,"Moderate Risk","High Risk")) -> Moderate Risk | S184: =IF(Patient_Data[[#This Row],[Age]]<=18,"Pediatric",IF(Patient_Data[[#This Row],[Age]]<=64,"Adult","Geriatric")) -> Adult
A185: NHM-2023-101808 | B185: =TEXT(Patient_Data!$E185,"mmmm") -> August | C185: =LEFT(B185,3) -> Aug | D185: =MONTH(Patient_Data!$E185) -> 8 | E185: 45891 | F185: =TEXT(Patient_Data[[#This Row],[Admission_Date]],"YYYY") -> 2025 | G185: Nancy Ford | H185: NovaHealth River Valley Hospital | I185: Female | J185: 41 | K185: Discharged | L185: 1 | M185: Emergency Room | N185: =IF(M185="Cardiology","Cardio",IF(M185="Intensive Care Unit","ICU",IF(M185="Neurology","Neuro",IF(M185="Emergency Room","ER",IF(M185="Pediatrics","PD",IF(M185="Surgery","Surgery",IF(M185="General Medicine","GM",IF(M185="Orthopedics","Ortho","")))))))) -> ER | O185: 8596.43 | P185: 5947.61 | Q185: 23.5 | R185: =IF(Patient_Data!$L185<2,"Low Risk",IF(Patient_Data!$L185<4,"Moderate Risk","High Risk")) -> Low Risk | S185: =IF(Patient_Data[[#This Row],[Age]]<=18,"Pediatric",IF(Patient_Data[[#This Row],[Age]]<=64,"Adult","Geriatric")) -> Adult
A186: NHM-2025-100193 | B186: =TEXT(Patient_Data!$E186,"mmmm") -> December | C186: =LEFT(B186,3) -> Dec | D186: =MONTH(Patient_Data!$E186) -> 12 | E186: 45999 | F186: =TEXT(Patient_Data[[#This Row],[Admission_Date]],"YYYY") -> 2025 | G186: Emma Jackson | H186: NovaHealth Chicago Medical Center | I186: Male | J186: 61 | K186: Discharged | L186: 1 | M186: Orthopedics | N186: =IF(M186="Cardiology","Cardio",IF(M186="Intensive Care Unit","ICU",IF(M186="Neurology","Neuro",IF(M186="Emergency Room","ER",IF(M186="Pediatrics","PD",IF(M186="Surgery","Surgery",IF(M186="General Medicine","GM",IF(M186="Orthopedics","Ortho","")))))))) -> Ortho | O186: 6247.97 | P186: 4460.78 | Q186: 10.9 | R186: =IF(Patient_Data!$L186<2,"Low Risk",IF(Patient_Data!$L186<4,"Moderate Risk","High Risk")) -> Low Risk | S186: =IF(Patient_Data[[#This Row],[Age]]<=18,"Pediatric",IF(Patient_Data[[#This Row],[Age]]<=64,"Adult","Geriatric")) -> Adult
... A322: NHM-2024-102209 | B322: =TEXT(Patient_Data!$E322,"mmmm") -> January | C322: =LEFT(B322,3) -> Jan | D322: =MONTH(Patient_Data!$E322) -> 1 | E322: 45666 | F322: =TEXT(Patient_Data[[#This Row],[Admission_Date]],"YYYY") -> 2025 | G322: Marilyn Graham | H322: NovaHealth Lakeside Medical Center | I322: Female | J322: 50 | K322: In-Patient Care | L322: 4 | M322: Surgery | N322: =IF(M322="Cardiology","Cardio",IF(M322="Intensive Care Unit","ICU",IF(M322="Neurology","Neuro",IF(M322="Emergency Room","ER",IF(M322="Pediatrics","PD",IF(M322="Surgery","Surgery",IF(M322="General Medicine","GM",IF(M322="Orthopedics","Ortho","")))))))) -> Surgery | O322: 21508.8 | P322: 12506.3 | Q322: 3.9 | R322: =IF(Patient_Data!$L322<2,"Low Risk",IF(Patient_Data!$L322<4,"Moderate Risk","High Risk")) -> High Risk | S322: =IF(Patient_Data[[#This Row],[Age]]<=18,"Pediatric",IF(Patient_Data[[#This Row],[Age]]<=64,"Adult","Geriatric")) -> Adult
A323: NHM-2024-102367 | B323: =TEXT(Patient_Data!$E323,"mmmm") -> April | C323: =LEFT(B323,3) -> Apr | D323: =MONTH(Patient_Data!$E323) -> 4 | E323: 46118 | F323: =TEXT(Patient_Data[[#This Row],[Admission_Date]],"YYYY") -> 2026 | G323: Ann Phillips | H323: NOVAHEALTH LAKESIDE MEDICAL CENTER | I323: Male | J323: 75 | K323: Discharged | L323: 2 | M323: Neurology | N323: =IF(M323="Cardiology","Cardio",IF(M323="Intensive Care Unit","ICU",IF(M323="Neurology","Neuro",IF(M323="Emergency Room","ER",IF(M323="Pediatrics","PD",IF(M323="Surgery","Surgery",IF(M323="General Medicine","GM",IF(M323="Orthopedics","Ortho","")))))))) -> Neuro | O323: 6050.17 | P323: 3690.6 | R323: =IF(Patient_Data!$L323<2,"Low Risk",IF(Patient_Data!$L323<4,"Moderate Risk","High Risk")) -> Moderate Risk | S323: =IF(Patient_Data[[#This Row],[Age]]<=18,"Pediatric",IF(Patient_Data[[#This Row],[Age]]<=64,"Adult","Geriatric")) -> Geriatric
A324: NHM-2023-101711 | B324: =TEXT(Patient_Data!$E324,"mmmm") -> October | C324: =LEFT(B324,3) -> Oct | D324: =MONTH(Patient_Data!$E324) -> 10 | E324: 45943 | F324: =TEXT(Patient_Data[[#This Row],[Admission_Date]],"YYYY") -> 2025 | G324: Betty Price | H324: NovaHealth Lakeside Medical Center | I324: Male | J324: 83 | K324: Discharged | L324: 1 | M324: General Medicine | N324: =IF(M324="Cardiology","Cardio",IF(M324="Intensive Care Unit","ICU",IF(M324="Neurology","Neuro",IF(M324="Emergency Room","ER",IF(M324="Pediatrics","PD",IF(M324="Surgery","Surgery",IF(M324="General Medicine","GM",IF(M324="Orthopedics","Ortho","")))))))) -> GM | O324: 2017.56 | P324: 1344.84 | Q324: 6.7 | R324: =IF(Patient_Data!$L324<2,"Low Risk",IF(Patient_Data!$L324<4,"Moderate Risk","High Risk")) -> Low Risk | S324: =IF(Patient_Data[[#This Row],[Age]]<=18,"Pediatric",IF(Patient_Data[[#This Row],[Age]]<=64,"Adult","Geriatric")) -> Geriatric
A325: NHM-2026-101243 | B325: =TEXT(Patient_Data!$E325,"mmmm") -> July | C325: =LEFT(B325,3) -> Jul | D325: =MONTH(Patient_Data!$E325) -> 7 | E325: 45855 | F325: =TEXT(Patient_Data[[#This Row],[Admission_Date]],"YYYY") -> 2025 | G325: Gerald Patterson | H325: NOVAHEALTH GREENFIELD CLINIC | I325: Male | J325: 39 | K325: Discharged | L325: 2 | M325: Neurology | N325: =IF(M325="Cardiology","Cardio",IF(M325="Intensive Care Unit","ICU",IF(M325="Neurology","Neuro",IF(M325="Emergency Room","ER",IF(M325="Pediatrics","PD",IF(M325="Surgery","Surgery",IF(M325="General Medicine","GM",IF(M325="Orthopedics","Ortho","")))))))) -> Neuro | O325: 10065.25 | P325: 6774.92 | Q325: 3.9 | R325: =IF(Patient_Data!$L325<2,"Low Risk",IF(Patient_Data!$L325<4,"Moderate Risk","High Risk")) -> Moderate Risk | S325: =IF(Patient_Data[[#This Row],[Age]]<=18,"Pediatric",IF(Patient_Data[[#This Row],[Age]]<=64,"Adult","Geriatric")) -> Adult
A326: NHM-2026-100057 | B326: =TEXT(Patient_Data!$E326,"mmmm") -> October | C326: =LEFT(B326,3) -> Oct | D326: =MONTH(Patient_Data!$E326) -> 10 | E326: 45225 | F326: =TEXT(Patient_Data[[#This Row],[Admission_Date]],"YYYY") -> 2023 | G326: Richard Bell | H326: NovaHealth Chicago Medical Center | I326: Male | J326: 51 | K326: Discharged | L326: 1 | M326: Orthopedics | N326: =IF(M326="Cardiology","Cardio",IF(M326="Intensive Care Unit","ICU",IF(M326="Neurology","Neuro",IF(M326="Emergency Room","ER",IF(M326="Pediatrics","PD",IF(M326="Surgery","Surgery",IF(M326="General Medicine","GM",IF(M326="Orthopedics","Ortho","")))))))) -> Ortho | O326: 8039.75 | P326: 5707.02 | Q326: 9.9 | R326: =IF(Patient_Data!$L326<2,"Low Risk",IF(Patient_Data!$L326<4,"Moderate Risk","High Risk")) -> Low Risk | S326: =IF(Patient_Data[[#This Row],[Age]]<=18,"Pediatric",IF(Patient_Data[[#This Row],[Age]]<=64,"Adult","Geriatric")) -> Adult
A327: NHM-2024-101317 | B327: =TEXT(Patient_Data!$E327,"mmmm") -> September | C327: =LEFT(B327,3) -> Sep | D327: =MONTH(Patient_Data!$E327) -> 9 | E327: 45539 | F327: =TEXT(Patient_Data[[#This Row],[Admission_Date]],"YYYY") -> 2024 | G327: Marilyn Sullivan | H327: NovaHealth Chicago Med. Center | I327: Female | J327: 20 | K327: Discharged | L327: 1 | M327: Cardiology | N327: =IF(M327="Cardiology","Cardio",IF(M327="Intensive Care Unit","ICU",IF(M327="Neurology","Neuro",IF(M327="Emergency Room","ER",IF(M327="Pediatrics","PD",IF(M327="Surgery","Surgery",IF(M327="General Medicine","GM",IF(M327="Orthopedics","Ortho","")))))))) -> Cardio | O327: 6863.9 | P327: 5010.65 | R327: =IF(Patient_Data!$L327<2,"Low Risk",IF(Patient_Data!$L327<4,"Moderate Risk","High Risk")) -> Low Risk | S327: =IF(Patient_Data[[#This Row],[Age]]<=18,"Pediatric",IF(Patient_Data[[#This Row],[Age]]<=64,"Adult","Geriatric")) -> Adult
A328: NHM-2025-100328 | B328: =TEXT(Patient_Data!$E328,"mmmm") -> September | C328: =LEFT(B328,3) -> Sep | D328: =MONTH(Patient_Data!$E328) -> 9 | E328: 45558 | F328: =TEXT(Patient_Data[[#This Row],[Admission_Date]],"YYYY") -> 2024 | G328: Patrick Lopez | H328: NovaHealth Metro General Hospital | I328: Male | J328: 74 | K328: Discharged | L328: 2 | M328: General Medicine | N328: =IF(M328="Cardiology","Cardio",IF(M328="Intensive Care Unit","ICU",IF(M328="Neurology","Neuro",IF(M328="Emergency Room","ER",IF(M328="Pediatrics","PD",IF(M328="Surgery","Surgery",IF(M328="General Medicine","GM",IF(M328="Orthopedics","Ortho","")))))))) -> GM | O328: 5043.27 | P328: 3884.89 | Q328: 6.5 | R328: =IF(Patient_Data!$L328<2,"Low Risk",IF(Patient_Data!$L328<4,"Moderate Risk","High Risk")) -> Moderate Risk | S328: =IF(Patient_Data[[#This Row],[Age]]<=18,"Pediatric",IF(Patient_Data[[#This Row],[Age]]<=64,"Adult","Geriatric")) -> Geriatric
A329: NHM-2025-100573 | B329: =TEXT(Patient_Data!$E329,"mmmm") -> February | C329: =LEFT(B329,3) -> Feb | D329: =MONTH(Patient_Data!$E329) -> 2 | E329: 45342 | F329: =TEXT(Patient_Data[[#This Row],[Admission_Date]],"YYYY") -> 2024 | G329: Samantha Murray | H329: novahealth oakridge community hospital | I329: Male | J329: 79 | K329: Discharged | L329: 1 | M329: General Medicine | N329: =IF(M329="Cardiology","Cardio",IF(M329="Intensive Care Unit","ICU",IF(M329="Neurology","Neuro",IF(M329="Emergency Room","ER",IF(M329="Pediatrics","PD",IF(M329="Surgery","Surgery",IF(M329="General Medicine","GM",IF(M329="Orthopedics","Ortho","")))))))) -> GM | O329: 2176.98 | P329: 1325.05 | Q329: 7.8 | R329: =IF(Patient_Data!$L329<2,"Low Risk",IF(Patient_Data!$L329<4,"Moderate Risk","High Risk")) -> Low Risk | S329: =IF(Patient_Data[[#This Row],[Age]]<=18,"Pediatric",IF(Patient_Data[[#This Row],[Age]]<=64,"Adult","Geriatric")) -> Geriatric
A330: NHM-2023-100922 | B330: =TEXT(Patient_Data!$E330,"mmmm") -> May | C330: =LEFT(B330,3) -> May | D330: =MONTH(Patient_Data!$E330) -> 5 | E330: 46167 | F330: =TEXT(Patient_Data[[#This Row],[Admission_Date]],"YYYY") -> 2026 | G330: Bryan Morgan | H330: NovaHealth Lakeside Medical Center | I330: Female | J330: 50 | K330: Discharged | L330: 1 | M330: Emergency Room | N330: =IF(M330="Cardiology","Cardio",IF(M330="Intensive Care Unit","ICU",IF(M330="Neurology","Neuro",IF(M330="Emergency Room","ER",IF(M330="Pediatrics","PD",IF(M330="Surgery","Surgery",IF(M330="General Medicine","GM",IF(M330="Orthopedics","Ortho","")))))))) -> ER | O330: 7262.05 | P330: 4591.45 | Q330: 20.2 | R330: =IF(Patient_Data!$L330<2,"Low Risk",IF(Patient_Data!$L330<4,"Moderate Risk","High Risk")) -> Low Risk | S330: =IF(Patient_Data[[#This Row],[Age]]<=18,"Pediatric",IF(Patient_Data[[#This Row],[Age]]<=64,"Adult","Geriatric")) -> Adult
A331: NHM-2023-102386 | B331: =TEXT(Patient_Data!$E331,"mmmm") -> January | C331: =LEFT(B331,3) -> Jan | D331: =MONTH(Patient_Data!$E331) -> 1 | E331: 45659 | F331: =TEXT(Patient_Data[[#This Row],[Admission_Date]],"YYYY") -> 2025 | G331: Maria Martinez | H331: NovaHealth Midtown Medical Center | I331: Female | J331: 62 | K331: Discharged | L331: 1 | M331: Neurology | N331: =IF(M331="Cardiology","Cardio",IF(M331="Intensive Care Unit","ICU",IF(M331="Neurology","Neuro",IF(M331="Emergency Room","ER",IF(M331="Pediatrics","PD",IF(M331="Surgery","Surgery",IF(M331="General Medicine","GM",IF(M331="Orthopedics","Ortho","")))))))) -> Neuro | O331: 9112.13 | P331: 5898.96 | Q331: 8.4 | R331: =IF(Patient_Data!$L331<2,"Low Risk",IF(Patient_Data!$L331<4,"Moderate Risk","High Risk")) -> Low Risk | S331: =IF(Patient_Data[[#This Row],[Age]]<=18,"Pediatric",IF(Patient_Data[[#This Row],[Age]]<=64,"Adult","Geriatric")) -> Adult
A332: NHM-2026-101331 | B332: =TEXT(Patient_Data!$E332,"mmmm") -> April | C332: =LEFT(B332,3) -> Apr | D332: =MONTH(Patient_Data!$E332) -> 4 | E332: 46142 | F332: =TEXT(Patient_Data[[#This Row],[Admission_Date]],"YYYY") -> 2026 | G332: Charles Hughes | H332: NovaHealth Northside Hospital | I332: Female | J332: 87 | K332: Discharged | L332: 2 | M332: Orthopedics | N332: =IF(M332="Cardiology","Cardio",IF(M332="Intensive Care Unit","ICU",IF(M332="Neurology","Neuro",IF(M332="Emergency Room","ER",IF(M332="Pediatrics","PD",IF(M332="Surgery","Surgery",IF(M332="General Medicine","GM",IF(M332="Orthopedics","Ortho","")))))))) -> Ortho | O332: 5260.42 | P332: 3574.08 | Q332: 6.2 | R332: =IF(Patient_Data!$L332<2,"Low Risk",IF(Patient_Data!$L332<4,"Moderate Risk","High Risk")) -> Moderate Risk | S332: =IF(Patient_Data[[#This Row],[Age]]<=18,"Pediatric",IF(Patient_Data[[#This Row],[Age]]<=64,"Adult","Geriatric")) -> Geriatric
A333: NHM-2026-101410 | B333: =TEXT(Patient_Data!$E333,"mmmm") -> October | C333: =LEFT(B333,3) -> Oct | D333: =MONTH(Patient_Data!$E333) -> 10 | E333: 45202 | F333: =TEXT(Patient_Data[[#This Row],[Admission_Date]],"YYYY") -> 2023 | G333: Joseph Campbell | H333: NovaHealth Northside Hospital | I333: Male | J333: 45 | K333: Discharged | L333: 1 | M333: Emergency Room | N333: =IF(M333="Cardiology","Cardio",IF(M333="Intensive Care Unit","ICU",IF(M333="Neurology","Neuro",IF(M333="Emergency Room","ER",IF(M333="Pediatrics","PD",IF(M333="Surgery","Surgery",IF(M333="General Medicine","GM",IF(M333="Orthopedics","Ortho","")))))))) -> ER | O333: 3426.59 | P333: 2513.01 | Q333: 14.3 | R333: =IF(Patient_Data!$L333<2,"Low Risk",IF(Patient_Data!$L333<4,"Moderate Risk","High Risk")) -> Low Risk | S333: =IF(Patient_Data[[#This Row],[Age]]<=18,"Pediatric",IF(Patient_Data[[#This Row],[Age]]<=64,"Adult","Geriatric")) -> Adult
A334: NHM-2024-101919 | B334: =TEXT(Patient_Data!$E334,"mmmm") -> March | C334: =LEFT(B334,3) -> Mar | D334: =MONTH(Patient_Data!$E334) -> 3 | E334: 45357 | F334: =TEXT(Patient_Data[[#This Row],[Admission_Date]],"YYYY") -> 2024 | G334: Denise Alexander | H334: NovaHealth Northside Hospital | I334: Female | J334: 79 | K334: Discharged | L334: 2 | M334: Cardiology | N334: =IF(M334="Cardiology","Cardio",IF(M334="Intensive Care Unit","ICU",IF(M334="Neurology","Neuro",IF(M334="Emergency Room","ER",IF(M334="Pediatrics","PD",IF(M334="Surgery","Surgery",IF(M334="General Medicine","GM",IF(M334="Orthopedics","Ortho","")))))))) -> Cardio | O334: 10471.86 | P334: 7729.26 | Q334: 10.6 | R334: =IF(Patient_Data!$L334<2,"Low Risk",IF(Patient_Data!$L334<4,"Moderate Risk","High Risk")) -> Moderate Risk | S334: =IF(Patient_Data[[#This Row],[Age]]<=18,"Pediatric",IF(Patient_Data[[#This Row],[Age]]<=64,"Adult","Geriatric")) -> Geriatric
A335: NHM-2024-100691 | B335: =TEXT(Patient_Data!$E335,"mmmm") -> April | C335: =LEFT(B335,3) -> Apr | D335: =MONTH(Patient_Data!$E335) -> 4 | E335: 45769 | F335: =TEXT(Patient_Data[[#This Row],[Admission_Date]],"YYYY") -> 2025 | G335: Nicholas Cruz | H335: NovaHealth Lakeside Medical Center | I335: Male | J335: 60 | K335: Discharged | L335: 1 | M335: Cardiology | N335: =IF(M335="Cardiology","Cardio",IF(M335="Intensive Care Unit","ICU",IF(M335="Neurology","Neuro",IF(M335="Emergency Room","ER",IF(M335="Pediatrics","PD",IF(M335="Surgery","Surgery",IF(M335="General Medicine","GM",IF(M335="Orthopedics","Ortho","")))))))) -> Cardio | O335: 11315.95 | P335: 8624.12 | Q335: 3 | R335: =IF(Patient_Data!$L335<2,"Low Risk",IF(Patient_Data!$L335<4,"Moderate Risk","High Risk")) -> Low Risk | S335: =IF(Patient_Data[[#This Row],[Age]]<=18,"Pediatric",IF(Patient_Data[[#This Row],[Age]]<=64,"Adult","Geriatric")) -> Adult
A336: NHM-2026-102307 | B336: =TEXT(Patient_Data!$E336,"mmmm") -> January | C336: =LEFT(B336,3) -> Jan | D336: =MONTH(Patient_Data!$E336) -> 1 | E336: 45665 | F336: =TEXT(Patient_Data[[#This Row],[Admission_Date]],"YYYY") -> 2025 | G336: Laura Gomez | H336: NovaHealth Greenfield Clinic | I336: Female | J336: 85 | K336: In-Patient Care | L336: 3 | M336: Surgery | N336: =IF(M336="Cardiology","Cardio",IF(M336="Intensive Care Unit","ICU",IF(M336="Neurology","Neuro",IF(M336="Emergency Room","ER",IF(M336="Pediatrics","PD",IF(M336="Surgery","Surgery",IF(M336="General Medicine","GM",IF(M336="Orthopedics","Ortho","")))))))) -> Surgery | O336: 15338.71 | P336: 8917.25 | Q336: 2.6 | R336: =IF(Patient_Data!$L336<2,"Low Risk",IF(Patient_Data!$L336<4,"Moderate Risk","High Risk")) -> Moderate Risk | S336: =IF(Patient_Data[[#This Row],[Age]]<=18,"Pediatric",IF(Patient_Data[[#This Row],[Age]]<=64,"Adult","Geriatric")) -> Geriatric
A337: NHM-2026-102047 | B337: =TEXT(Patient_Data!$E337,"mmmm") -> September | C337: =LEFT(B337,3) -> Sep | D337: =MONTH(Patient_Data!$E337) -> 9 | E337: 45922 | F337: =TEXT(Patient_Data[[#This Row],[Admission_Date]],"YYYY") -> 2025 | G337: Jasmine Mcdonald | H337: NovaHealth Northside Hospital | I337: Female | J337: 57 | K337: Discharged | L337: 2 | M337: Cardiology | N337: =IF(M337="Cardiology","Cardio",IF(M337="Intensive Care Unit","ICU",IF(M337="Neurology","Neuro",IF(M337="Emergency Room","ER",IF(M337="Pediatrics","PD",IF(M337="Surgery","Surgery",IF(M337="General Medicine","GM",IF(M337="Orthopedics","Ortho","")))))))) -> Cardio | O337: 12398.33 | P337: 7614.18 | Q337: 6.4 | R337: =IF(Patient_Data!$L337<2,"Low Risk",IF(Patient_Data!$L337<4,"Moderate Risk","High Risk")) -> Moderate Risk | S337: =IF(Patient_Data[[#This Row],[Age]]<=18,"Pediatric",IF(Patient_Data[[#This Row],[Age]]<=64,"Adult","Geriatric")) -> Adult
A338: NHM-2026-100149 | B338: =TEXT(Patient_Data!$E338,"mmmm") -> April | C338: =LEFT(B338,3) -> Apr | D338: =MONTH(Patient_Data!$E338) -> 4 | E338: 46136 | F338: =TEXT(Patient_Data[[#This Row],[Admission_Date]],"YYYY") -> 2026 | G338: Lisa Adams | H338: NovaHealth Chicago Medical Center | I338: Female | J338: 64 | K338: Readmitted | L338: 5 | M338: Intensive Care Unit | N338: =IF(M338="Cardiology","Cardio",IF(M338="Intensive Care Unit","ICU",IF(M338="Neurology","Neuro",IF(M338="Emergency Room","ER",IF(M338="Pediatrics","PD",IF(M338="Surgery","Surgery",IF(M338="General Medicine","GM",IF(M338="Orthopedics","Ortho","")))))))) -> ICU | O338: 25334.61 | P338: 16328.55 | Q338: 14.3 | R338: =IF(Patient_Data!$L338<2,"Low Risk",IF(Patient_Data!$L338<4,"Moderate Risk","High Risk")) -> High Risk | S338: =IF(Patient_Data[[#This Row],[Age]]<=18,"Pediatric",IF(Patient_Data[[#This Row],[Age]]<=64,"Adult","Geriatric")) -> Adult
A339: NHM-2023-100043 | B339: =TEXT(Patient_Data!$E339,"mmmm") -> January | C339: =LEFT(B339,3) -> Jan | D339: =MONTH(Patient_Data!$E339) -> 1 | E339: 45681 | F339: =TEXT(Patient_Data[[#This Row],[Admission_Date]],"YYYY") -> 2025 | G339: Aaron Johnson | H339: NovaHealth River Valley Hospital | I339: Female | J339: 28 | K339: Discharged | L339: 1 | M339: Neurology | N339: =IF(M339="Cardiology","Cardio",IF(M339="Intensive Care Unit","ICU",IF(M339="Neurology","Neuro",IF(M339="Emergency Room","ER",IF(M339="Pediatrics","PD",IF(M339="Surgery","Surgery",IF(M339="General Medicine","GM",IF(M339="Orthopedics","Ortho","")))))))) -> Neuro | O339: 4236.24 | P339: 2904.68 | Q339: 8.3 | R339: =IF(Patient_Data!$L339<2,"Low Risk",IF(Patient_Data!$L339<4,"Moderate Risk","High Risk")) -> Low Risk | S339: =IF(Patient_Data[[#This Row],[Age]]<=18,"Pediatric",IF(Patient_Data[[#This Row],[Age]]<=64,"Adult","Geriatric")) -> Adult
... A363: NHM-2024-102282 | B363: =TEXT(Patient_Data!$E363,"mmmm") -> November | C363: =LEFT(B363,3) -> Nov | D363: =MONTH(Patient_Data!$E363) -> 11 | E363: 45987 | F363: =TEXT(Patient_Data[[#This Row],[Admission_Date]],"YYYY") -> 2025 | G363: Jonathan Ramos | H363: NovaHealth Chicago Medical Center | I363: Male | J363: 40 | K363: Discharged | L363: 1 | M363: Cardiology | N363: =IF(M363="Cardiology","Cardio",IF(M363="Intensive Care Unit","ICU",IF(M363="Neurology","Neuro",IF(M363="Emergency Room","ER",IF(M363="Pediatrics","PD",IF(M363="Surgery","Surgery",IF(M363="General Medicine","GM",IF(M363="Orthopedics","Ortho","")))))))) -> Cardio | O363: 5971.1 | P363: 4562.04 | Q363: 3 | R363: =IF(Patient_Data!$L363<2,"Low Risk",IF(Patient_Data!$L363<4,"Moderate Risk","High Risk")) -> Low Risk | S363: =IF(Patient_Data[[#This Row],[Age]]<=18,"Pediatric",IF(Patient_Data[[#This Row],[Age]]<=64,"Adult","Geriatric")) -> Adult
A364: NHM-2023-100728 | B364: =TEXT(Patient_Data!$E364,"mmmm") -> June | C364: =LEFT(B364,3) -> Jun | D364: =MONTH(Patient_Data!$E364) -> 6 | E364: 46174 | F364: =TEXT(Patient_Data[[#This Row],[Admission_Date]],"YYYY") -> 2026 | G364: Jeffrey Howard | H364: NovaHealth River Valley Hospital | I364: Female | J364: 23 | K364: Discharged | L364: 3 | M364: General Medicine | N364: =IF(M364="Cardiology","Cardio",IF(M364="Intensive Care Unit","ICU",IF(M364="Neurology","Neuro",IF(M364="Emergency Room","ER",IF(M364="Pediatrics","PD",IF(M364="Surgery","Surgery",IF(M364="General Medicine","GM",IF(M364="Orthopedics","Ortho","")))))))) -> GM | O364: 2883.59 | P364: 1672.48 | R364: =IF(Patient_Data!$L364<2,"Low Risk",IF(Patient_Data!$L364<4,"Moderate Risk","High Risk")) -> Moderate Risk | S364: =IF(Patient_Data[[#This Row],[Age]]<=18,"Pediatric",IF(Patient_Data[[#This Row],[Age]]<=64,"Adult","Geriatric")) -> Adult
A365: NHM-2024-100554 | B365: =TEXT(Patient_Data!$E365,"mmmm") -> May | C365: =LEFT(B365,3) -> May | D365: =MONTH(Patient_Data!$E365) -> 5 | E365: 45789 | F365: =TEXT(Patient_Data[[#This Row],[Admission_Date]],"YYYY") -> 2025 | G365: Nicole Long | H365: NovaHealth Lakeside Medical Center | I365: Female | J365: 25 | K365: In-Patient Care | L365: 3 | M365: Cardiology | N365: =IF(M365="Cardiology","Cardio",IF(M365="Intensive Care Unit","ICU",IF(M365="Neurology","Neuro",IF(M365="Emergency Room","ER",IF(M365="Pediatrics","PD",IF(M365="Surgery","Surgery",IF(M365="General Medicine","GM",IF(M365="Orthopedics","Ortho","")))))))) -> Cardio | O365: 9835.27 | P365: 6033.91 | Q365: 4.3 | R365: =IF(Patient_Data!$L365<2,"Low Risk",IF(Patient_Data!$L365<4,"Moderate Risk","High Risk")) -> Moderate Risk | S365: =IF(Patient_Data[[#This Row],[Age]]<=18,"Pediatric",IF(Patient_Data[[#This Row],[Age]]<=64,"Adult","Geriatric")) -> Adult
A366: NHM-2026-100294 | B366: =TEXT(Patient_Data!$E366,"mmmm") -> February | C366: =LEFT(B366,3) -> Feb | D366: =MONTH(Patient_Data!$E366) -> 2 | E366: 45341 | F366: =TEXT(Patient_Data[[#This Row],[Admission_Date]],"YYYY") -> 2024 | G366: Terry Edwards | H366: NovaHealth Greenfield Clinic | I366: Female | J366: 35 | K366: Discharged | L366: 1 | M366: Emergency Room | N366: =IF(M366="Cardiology","Cardio",IF(M366="Intensive Care Unit","ICU",IF(M366="Neurology","Neuro",IF(M366="Emergency Room","ER",IF(M366="Pediatrics","PD",IF(M366="Surgery","Surgery",IF(M366="General Medicine","GM",IF(M366="Orthopedics","Ortho","")))))))) -> ER | O366: 5608.66 | P366: 3688.74 | Q366: 12.4 | R366: =IF(Patient_Data!$L366<2,"Low Risk",IF(Patient_Data!$L366<4,"Moderate Risk","High Risk")) -> Low Risk | S366: =IF(Patient_Data[[#This Row],[Age]]<=18,"Pediatric",IF(Patient_Data[[#This Row],[Age]]<=64,"Adult","Geriatric")) -> Adult
A367: NHM-2023-101509 | B367: =TEXT(Patient_Data!$E367,"mmmm") -> January | C367: =LEFT(B367,3) -> Jan | D367: =MONTH(Patient_Data!$E367) -> 1 | E367: 45675 | F367: =TEXT(Patient_Data[[#This Row],[Admission_Date]],"YYYY") -> 2025 | G367: Vincent Sullivan | H367: NovaHealth Oakridge Community Hospital | I367: Male | J367: 76 | K367: Readmitted | L367: 4 | M367: Surgery | N367: =IF(M367="Cardiology","Cardio",IF(M367="Intensive Care Unit","ICU",IF(M367="Neurology","Neuro",IF(M367="Emergency Room","ER",IF(M367="Pediatrics","PD",IF(M367="Surgery","Surgery",IF(M367="General Medicine","GM",IF(M367="Orthopedics","Ortho","")))))))) -> Surgery | O367: 14333.62 | P367: 9665.13 | Q367: 7.7 | R367: =IF(Patient_Data!$L367<2,"Low Risk",IF(Patient_Data!$L367<4,"Moderate Risk","High Risk")) -> High Risk | S367: =IF(Patient_Data[[#This Row],[Age]]<=18,"Pediatric",IF(Patient_Data[[#This Row],[Age]]<=64,"Adult","Geriatric")) -> Geriatric
A368: NHM-2024-101864 | B368: =TEXT(Patient_Data!$E368,"mmmm") -> December | C368: =LEFT(B368,3) -> Dec | D368: =MONTH(Patient_Data!$E368) -> 12 | E368: 45629 | F368: =TEXT(Patient_Data[[#This Row],[Admission_Date]],"YYYY") -> 2024 | G368: Christine Howard | H368: NovaHealth Midtown Medical Center | I368: Female | J368: 22 | K368: Discharged | L368: 1 | M368: General Medicine | N368: =IF(M368="Cardiology","Cardio",IF(M368="Intensive Care Unit","ICU",IF(M368="Neurology","Neuro",IF(M368="Emergency Room","ER",IF(M368="Pediatrics","PD",IF(M368="Surgery","Surgery",IF(M368="General Medicine","GM",IF(M368="Orthopedics","Ortho","")))))))) -> GM | O368: 1265.06 | P368: 935.94 | Q368: 6.3 | R368: =IF(Patient_Data!$L368<2,"Low Risk",IF(Patient_Data!$L368<4,"Moderate Risk","High Risk")) -> Low Risk | S368: =IF(Patient_Data[[#This Row],[Age]]<=18,"Pediatric",IF(Patient_Data[[#This Row],[Age]]<=64,"Adult","Geriatric")) -> Adult
A369: NHM-2025-101267 | B369: =TEXT(Patient_Data!$E369,"mmmm") -> October | C369: =LEFT(B369,3) -> Oct | D369: =MONTH(Patient_Data!$E369) -> 10 | E369: 45946 | F369: =TEXT(Patient_Data[[#This Row],[Admission_Date]],"YYYY") -> 2025 | G369: Ronald Reyes | H369: NovaHealth Greenfield Clinic | I369: Female | J369: 37 | K369: In-Patient Care | L369: 2 | M369: Cardiology | N369: =IF(M369="Cardiology","Cardio",IF(M369="Intensive Care Unit","ICU",IF(M369="Neurology","Neuro",IF(M369="Emergency Room","ER",IF(M369="Pediatrics","PD",IF(M369="Surgery","Surgery",IF(M369="General Medicine","GM",IF(M369="Orthopedics","Ortho","")))))))) -> Cardio | O369: 12305.62 | P369: 9047.9 | Q369: 8.1 | R369: =IF(Patient_Data!$L369<2,"Low Risk",IF(Patient_Data!$L369<4,"Moderate Risk","High Risk")) -> Moderate Risk | S369: =IF(Patient_Data[[#This Row],[Age]]<=18,"Pediatric",IF(Patient_Data[[#This Row],[Age]]<=64,"Adult","Geriatric")) -> Adult
A370: NHM-2023-102329 | B370: =TEXT(Patient_Data!$E370,"mmmm") -> April | C370: =LEFT(B370,3) -> Apr | D370: =MONTH(Patient_Data!$E370) -> 4 | E370: 45775 | F370: =TEXT(Patient_Data[[#This Row],[Admission_Date]],"YYYY") -> 2025 | G370: Edward Patel | H370: NovaHealth Midtown Medical Center | I370: Female | J370: 47 | K370: Readmitted | L370: 4 | M370: Neurology | N370: =IF(M370="Cardiology","Cardio",IF(M370="Intensive Care Unit","ICU",IF(M370="Neurology","Neuro",IF(M370="Emergency Room","ER",IF(M370="Pediatrics","PD",IF(M370="Surgery","Surgery",IF(M370="General Medicine","GM",IF(M370="Orthopedics","Ortho","")))))))) -> Neuro | O370: 12623.61 | P370: 9617.94 | Q370: 3 | R370: =IF(Patient_Data!$L370<2,"Low Risk",IF(Patient_Data!$L370<4,"Moderate Risk","High Risk")) -> High Risk | S370: =IF(Patient_Data[[#This Row],[Age]]<=18,"Pediatric",IF(Patient_Data[[#This Row],[Age]]<=64,"Adult","Geriatric")) -> Adult
A371: NHM-2026-102148 | B371: =TEXT(Patient_Data!$E371,"mmmm") -> January | C371: =LEFT(B371,3) -> Jan | D371: =MONTH(Patient_Data!$E371) -> 1 | E371: 46045 | F371: =TEXT(Patient_Data[[#This Row],[Admission_Date]],"YYYY") -> 2026 | G371: Randy Diaz | H371: NovaHealth Northside Hospital | I371: Female | J371: 79 | K371: Discharged | L371: 2 | M371: Emergency Room | N371: =IF(M371="Cardiology","Cardio",IF(M371="Intensive Care Unit","ICU",IF(M371="Neurology","Neuro",IF(M371="Emergency Room","ER",IF(M371="Pediatrics","PD",IF(M371="Surgery","Surgery",IF(M371="General Medicine","GM",IF(M371="Orthopedics","Ortho","")))))))) -> ER | O371: 3188.97 | P371: 2028 | Q371: 22.3 | R371: =IF(Patient_Data!$L371<2,"Low Risk",IF(Patient_Data!$L371<4,"Moderate Risk","High Risk")) -> Moderate Risk | S371: =IF(Patient_Data[[#This Row],[Age]]<=18,"Pediatric",IF(Patient_Data[[#This Row],[Age]]<=64,"Adult","Geriatric")) -> Geriatric
A372: NHM-2023-101304 | B372: =TEXT(Patient_Data!$E372,"mmmm") -> May | C372: =LEFT(B372,3) -> May | D372: =MONTH(Patient_Data!$E372) -> 5 | E372: 45792 | F372: =TEXT(Patient_Data[[#This Row],[Admission_Date]],"YYYY") -> 2025 | G372: Zachary Lee | H372: NovaHealth Greenfield Clinic | I372: Female | J372: 19 | K372: Discharged | L372: 1 | M372: General Medicine | N372: =IF(M372="Cardiology","Cardio",IF(M372="Intensive Care Unit","ICU",IF(M372="Neurology","Neuro",IF(M372="Emergency Room","ER",IF(M372="Pediatrics","PD",IF(M372="Surgery","Surgery",IF(M372="General Medicine","GM",IF(M372="Orthopedics","Ortho","")))))))) -> GM | O372: 3565.17 | P372: 2206.75 | Q372: 4 | R372: =IF(Patient_Data!$L372<2,"Low Risk",IF(Patient_Data!$L372<4,"Moderate Risk","High Risk")) -> Low Risk | S372: =IF(Patient_Data[[#This Row],[Age]]<=18,"Pediatric",IF(Patient_Data[[#This Row],[Age]]<=64,"Adult","Geriatric")) -> Adult
A373: NHM-2025-102023 | B373: =TEXT(Patient_Data!$E373,"mmmm") -> March | C373: =LEFT(B373,3) -> Mar | D373: =MONTH(Patient_Data!$E373) -> 3 | E373: 45370 | F373: =TEXT(Patient_Data[[#This Row],[Admission_Date]],"YYYY") -> 2024 | G373: Sean Garcia | H373: NovaHealth Lakeside Medical Center | I373: Male | J373: 67 | K373: In-Patient Care | L373: 3 | M373: Cardiology | N373: =IF(M373="Cardiology","Cardio",IF(M373="Intensive Care Unit","ICU",IF(M373="Neurology","Neuro",IF(M373="Emergency Room","ER",IF(M373="Pediatrics","PD",IF(M373="Surgery","Surgery",IF(M373="General Medicine","GM",IF(M373="Orthopedics","Ortho","")))))))) -> Cardio | O373: 6314.26 | P373: 4119.53 | Q373: 9.8 | R373: =IF(Patient_Data!$L373<2,"Low Risk",IF(Patient_Data!$L373<4,"Moderate Risk","High Risk")) -> Moderate Risk | S373: =IF(Patient_Data[[#This Row],[Age]]<=18,"Pediatric",IF(Patient_Data[[#This Row],[Age]]<=64,"Adult","Geriatric")) -> Geriatric
A374: NHM-2026-100891 | B374: =TEXT(Patient_Data!$E374,"mmmm") -> February | C374: =LEFT(B374,3) -> Feb | D374: =MONTH(Patient_Data!$E374) -> 2 | E374: 45708 | F374: =TEXT(Patient_Data[[#This Row],[Admission_Date]],"YYYY") -> 2025 | G374: Ruth White | H374: NovaHealth River Valley Hospital | I374: Female | J374: 55 | K374: In-Patient Care | L374: 1 | M374: Cardiology | N374: =IF(M374="Cardiology","Cardio",IF(M374="Intensive Care Unit","ICU",IF(M374="Neurology","Neuro",IF(M374="Emergency Room","ER",IF(M374="Pediatrics","PD",IF(M374="Surgery","Surgery",IF(M374="General Medicine","GM",IF(M374="Orthopedics","Ortho","")))))))) -> Cardio | O374: 5681.41 | P374: 3901.74 | Q374: 11.9 | R374: =IF(Patient_Data!$L374<2,"Low Risk",IF(Patient_Data!$L374<4,"Moderate Risk","High Risk")) -> Low Risk | S374: =IF(Patient_Data[[#This Row],[Age]]<=18,"Pediatric",IF(Patient_Data[[#This Row],[Age]]<=64,"Adult","Geriatric")) -> Adult
A375: NHM-2026-102050 | B375: =TEXT(Patient_Data!$E375,"mmmm") -> July | C375: =LEFT(B375,3) -> Jul | D375: =MONTH(Patient_Data!$E375) -> 7 | E375: 45487 | F375: =TEXT(Patient_Data[[#This Row],[Admission_Date]],"YYYY") -> 2024 | G375: Jennifer Coleman | H375: NovaHealth Metro General Hospital | I375: Female | J375: 59 | K375: Discharged | L375: 3 | M375: Surgery | N375: =IF(M375="Cardiology","Cardio",IF(M375="Intensive Care Unit","ICU",IF(M375="Neurology","Neuro",IF(M375="Emergency Room","ER",IF(M375="Pediatrics","PD",IF(M375="Surgery","Surgery",IF(M375="General Medicine","GM",IF(M375="Orthopedics","Ortho","")))))))) -> Surgery | O375: 11984.83 | P375: 8422.98 | Q375: 4.2 | R375: =IF(Patient_Data!$L375<2,"Low Risk",IF(Patient_Data!$L375<4,"Moderate Risk","High Risk")) -> Moderate Risk | S375: =IF(Patient_Data[[#This Row],[Age]]<=18,"Pediatric",IF(Patient_Data[[#This Row],[Age]]<=64,"Adult","Geriatric")) -> Adult
A376: NHM-2024-100741 | B376: =TEXT(Patient_Data!$E376,"mmmm") -> April | C376: =LEFT(B376,3) -> Apr | D376: =MONTH(Patient_Data!$E376) -> 4 | E376: 46129 | F376: =TEXT(Patient_Data[[#This Row],[Admission_Date]],"YYYY") -> 2026 | G376: Katherine Davis | H376: NovaHealth Metro General Hospital | I376: Male | J376: 51 | K376: Discharged | L376: 2 | M376: Cardiology | N376: =IF(M376="Cardiology","Cardio",IF(M376="Intensive Care Unit","ICU",IF(M376="Neurology","Neuro",IF(M376="Emergency Room","ER",IF(M376="Pediatrics","PD",IF(M376="Surgery","Surgery",IF(M376="General Medicine","GM",IF(M376="Orthopedics","Ortho","")))))))) -> Cardio | O376: 8591.21 | P376: 6309.98 | Q376: 4.8 | R376: =IF(Patient_Data!$L376<2,"Low Risk",IF(Patient_Data!$L376<4,"Moderate Risk","High Risk")) -> Moderate Risk | S376: =IF(Patient_Data[[#This Row],[Age]]<=18,"Pediatric",IF(Patient_Data[[#This Row],[Age]]<=64,"Adult","Geriatric")) -> Adult
... A426: NHM-2026-101627 | B426: =TEXT(Patient_Data!$E426,"mmmm") -> April | C426: =LEFT(B426,3) -> Apr | D426: =MONTH(Patient_Data!$E426) -> 4 | E426: 45756 | F426: =TEXT(Patient_Data[[#This Row],[Admission_Date]],"YYYY") -> 2025 | G426: Samantha Sanchez | H426: NovaHealth Lakeshore Regional Center | I426: Female | J426: 87 | K426: In-Patient Care | L426: 4 | M426: Intensive Care Unit | N426: =IF(M426="Cardiology","Cardio",IF(M426="Intensive Care Unit","ICU",IF(M426="Neurology","Neuro",IF(M426="Emergency Room","ER",IF(M426="Pediatrics","PD",IF(M426="Surgery","Surgery",IF(M426="General Medicine","GM",IF(M426="Orthopedics","Ortho","")))))))) -> ICU | O426: 10681.38 | P426: 8182.65 | Q426: 8.1 | R426: =IF(Patient_Data!$L426<2,"Low Risk",IF(Patient_Data!$L426<4,"Moderate Risk","High Risk")) -> High Risk | S426: =IF(Patient_Data[[#This Row],[Age]]<=18,"Pediatric",IF(Patient_Data[[#This Row],[Age]]<=64,"Adult","Geriatric")) -> Geriatric
A427: NHM-2025-101636 | B427: =TEXT(Patient_Data!$E427,"mmmm") -> February | C427: =LEFT(B427,3) -> Feb | D427: =MONTH(Patient_Data!$E427) -> 2 | E427: 46064 | F427: =TEXT(Patient_Data[[#This Row],[Admission_Date]],"YYYY") -> 2026 | G427: Gloria Patterson | H427: NovaHealth Lakeside Medical Center | I427: Male | J427: 47 | K427: In-Patient Care | L427: 5 | M427: Surgery | N427: =IF(M427="Cardiology","Cardio",IF(M427="Intensive Care Unit","ICU",IF(M427="Neurology","Neuro",IF(M427="Emergency Room","ER",IF(M427="Pediatrics","PD",IF(M427="Surgery","Surgery",IF(M427="General Medicine","GM",IF(M427="Orthopedics","Ortho","")))))))) -> Surgery | O427: 21429.86 | P427: 12429.32 | R427: =IF(Patient_Data!$L427<2,"Low Risk",IF(Patient_Data!$L427<4,"Moderate Risk","High Risk")) -> High Risk | S427: =IF(Patient_Data[[#This Row],[Age]]<=18,"Pediatric",IF(Patient_Data[[#This Row],[Age]]<=64,"Adult","Geriatric")) -> Adult
A428: NHM-2024-101684 | B428: =TEXT(Patient_Data!$E428,"mmmm") -> May | C428: =LEFT(B428,3) -> May | D428: =MONTH(Patient_Data!$E428) -> 5 | E428: 46159 | F428: =TEXT(Patient_Data[[#This Row],[Admission_Date]],"YYYY") -> 2026 | G428: Nicholas Kim | H428: NovaHealth Greenfield Clinic | I428: Male | J428: 9 | K428: Discharged | L428: 1 | M428: Pediatrics | N428: =IF(M428="Cardiology","Cardio",IF(M428="Intensive Care Unit","ICU",IF(M428="Neurology","Neuro",IF(M428="Emergency Room","ER",IF(M428="Pediatrics","PD",IF(M428="Surgery","Surgery",IF(M428="General Medicine","GM",IF(M428="Orthopedics","Ortho","")))))))) -> PD | O428: 1877.9 | P428: 1169.52 | Q428: 3 | R428: =IF(Patient_Data!$L428<2,"Low Risk",IF(Patient_Data!$L428<4,"Moderate Risk","High Risk")) -> Low Risk | S428: =IF(Patient_Data[[#This Row],[Age]]<=18,"Pediatric",IF(Patient_Data[[#This Row],[Age]]<=64,"Adult","Geriatric")) -> Pediatric
A429: NHM-2026-100751 | B429: =TEXT(Patient_Data!$E429,"mmmm") -> December | C429: =LEFT(B429,3) -> Dec | D429: =MONTH(Patient_Data!$E429) -> 12 | E429: 45657 | F429: =TEXT(Patient_Data[[#This Row],[Admission_Date]],"YYYY") -> 2024 | G429: Brenda Barnes | H429: NovaHealth Lakeside Medical Center | I429: Male | J429: 81 | K429: Discharged | L429: 3 | M429: Orthopedics | N429: =IF(M429="Cardiology","Cardio",IF(M429="Intensive Care Unit","ICU",IF(M429="Neurology","Neuro",IF(M429="Emergency Room","ER",IF(M429="Pediatrics","PD",IF(M429="Surgery","Surgery",IF(M429="General Medicine","GM",IF(M429="Orthopedics","Ortho","")))))))) -> Ortho | O429: 10687.19 | P429: 6896.6 | Q429: 7.1 | R429: =IF(Patient_Data!$L429<2,"Low Risk",IF(Patient_Data!$L429<4,"Moderate Risk","High Risk")) -> Moderate Risk | S429: =IF(Patient_Data[[#This Row],[Age]]<=18,"Pediatric",IF(Patient_Data[[#This Row],[Age]]<=64,"Adult","Geriatric")) -> Geriatric
A430: NHM-2026-102069 | B430: =TEXT(Patient_Data!$E430,"mmmm") -> July | C430: =LEFT(B430,3) -> Jul | D430: =MONTH(Patient_Data!$E430) -> 7 | E430: 45491 | F430: =TEXT(Patient_Data[[#This Row],[Admission_Date]],"YYYY") -> 2024 | G430: Wayne Jenkins | H430: NovaHealth Lakeside Medical Center | I430: Male | J430: 40 | K430: Discharged | L430: 2 | M430: Emergency Room | N430: =IF(M430="Cardiology","Cardio",IF(M430="Intensive Care Unit","ICU",IF(M430="Neurology","Neuro",IF(M430="Emergency Room","ER",IF(M430="Pediatrics","PD",IF(M430="Surgery","Surgery",IF(M430="General Medicine","GM",IF(M430="Orthopedics","Ortho","")))))))) -> ER | O430: 6271.56 | P430: 4284.35 | Q430: 10.3 | R430: =IF(Patient_Data!$L430<2,"Low Risk",IF(Patient_Data!$L430<4,"Moderate Risk","High Risk")) -> Moderate Risk | S430: =IF(Patient_Data[[#This Row],[Age]]<=18,"Pediatric",IF(Patient_Data[[#This Row],[Age]]<=64,"Adult","Geriatric")) -> Adult
A431: NHM-2023-100478 | B431: =TEXT(Patient_Data!$E431,"mmmm") -> May | C431: =LEFT(B431,3) -> May | D431: =MONTH(Patient_Data!$E431) -> 5 | E431: 45803 | F431: =TEXT(Patient_Data[[#This Row],[Admission_Date]],"YYYY") -> 2025 | G431: Amanda Johnson | H431: NovaHealth Metro General Hospital | I431: Female | J431: 32 | K431: Discharged | L431: 1 | M431: Emergency Room | N431: =IF(M431="Cardiology","Cardio",IF(M431="Intensive Care Unit","ICU",IF(M431="Neurology","Neuro",IF(M431="Emergency Room","ER",IF(M431="Pediatrics","PD",IF(M431="Surgery","Surgery",IF(M431="General Medicine","GM",IF(M431="Orthopedics","Ortho","")))))))) -> ER | O431: 8361.39 | P431: 6043.37 | Q431: 23.8 | R431: =IF(Patient_Data!$L431<2,"Low Risk",IF(Patient_Data!$L431<4,"Moderate Risk","High Risk")) -> Low Risk | S431: =IF(Patient_Data[[#This Row],[Age]]<=18,"Pediatric",IF(Patient_Data[[#This Row],[Age]]<=64,"Adult","Geriatric")) -> Adult
A432: NHM-2025-100727 | B432: =TEXT(Patient_Data!$E432,"mmmm") -> September | C432: =LEFT(B432,3) -> Sep | D432: =MONTH(Patient_Data!$E432) -> 9 | E432: 45195 | F432: =TEXT(Patient_Data[[#This Row],[Admission_Date]],"YYYY") -> 2023 | G432: Patrick Allen | H432: NovaHealth Lakeshore Regional Center | I432: Female | J432: 84 | K432: In-Patient Care | L432: 4 | M432: Orthopedics | N432: =IF(M432="Cardiology","Cardio",IF(M432="Intensive Care Unit","ICU",IF(M432="Neurology","Neuro",IF(M432="Emergency Room","ER",IF(M432="Pediatrics","PD",IF(M432="Surgery","Surgery",IF(M432="General Medicine","GM",IF(M432="Orthopedics","Ortho","")))))))) -> Ortho | O432: 13446.41 | P432: 9871.88 | Q432: 7 | R432: =IF(Patient_Data!$L432<2,"Low Risk",IF(Patient_Data!$L432<4,"Moderate Risk","High Risk")) -> High Risk | S432: =IF(Patient_Data[[#This Row],[Age]]<=18,"Pediatric",IF(Patient_Data[[#This Row],[Age]]<=64,"Adult","Geriatric")) -> Geriatric
A433: NHM-2025-102272 | B433: =TEXT(Patient_Data!$E433,"mmmm") -> December | C433: =LEFT(B433,3) -> Dec | D433: =MONTH(Patient_Data!$E433) -> 12 | E433: 46002 | F433: =TEXT(Patient_Data[[#This Row],[Admission_Date]],"YYYY") -> 2025 | G433: Alan Ward | H433: NovaHealth Lakeside Medical Center | I433: Female | J433: 27 | K433: In-Patient Care | L433: 4 | M433: Cardiology | N433: =IF(M433="Cardiology","Cardio",IF(M433="Intensive Care Unit","ICU",IF(M433="Neurology","Neuro",IF(M433="Emergency Room","ER",IF(M433="Pediatrics","PD",IF(M433="Surgery","Surgery",IF(M433="General Medicine","GM",IF(M433="Orthopedics","Ortho","")))))))) -> Cardio | O433: 10822.58 | P433: 8308.36 | Q433: 10.4 | R433: =IF(Patient_Data!$L433<2,"Low Risk",IF(Patient_Data!$L433<4,"Moderate Risk","High Risk")) -> High Risk | S433: =IF(Patient_Data[[#This Row],[Age]]<=18,"Pediatric",IF(Patient_Data[[#This Row],[Age]]<=64,"Adult","Geriatric")) -> Adult
A434: NHM-2023-100140 | B434: =TEXT(Patient_Data!$E434,"mmmm") -> March | C434: =LEFT(B434,3) -> Mar | D434: =MONTH(Patient_Data!$E434) -> 3 | E434: 45357 | F434: =TEXT(Patient_Data[[#This Row],[Admission_Date]],"YYYY") -> 2024 | G434: Linda Hunter | H434: NovaHealth River Valley Hospital | I434: Female | J434: 12 | K434: In-Patient Care | L434: 3 | M434: Pediatrics | N434: =IF(M434="Cardiology","Cardio",IF(M434="Intensive Care Unit","ICU",IF(M434="Neurology","Neuro",IF(M434="Emergency Room","ER",IF(M434="Pediatrics","PD",IF(M434="Surgery","Surgery",IF(M434="General Medicine","GM",IF(M434="Orthopedics","Ortho","")))))))) -> PD | O434: 1697.78 | P434: 985.51 | Q434: 0.1 | R434: =IF(Patient_Data!$L434<2,"Low Risk",IF(Patient_Data!$L434<4,"Moderate Risk","High Risk")) -> Moderate Risk | S434: =IF(Patient_Data[[#This Row],[Age]]<=18,"Pediatric",IF(Patient_Data[[#This Row],[Age]]<=64,"Adult","Geriatric")) -> Pediatric
A435: NHM-2024-100118 | B435: =TEXT(Patient_Data!$E435,"mmmm") -> April | C435: =LEFT(B435,3) -> Apr | D435: =MONTH(Patient_Data!$E435) -> 4 | E435: 45399 | F435: =TEXT(Patient_Data[[#This Row],[Admission_Date]],"YYYY") -> 2024 | G435: Eugene Woods | H435: NovaHealth Lakeshore Regional Center | I435: Female | J435: 33 | K435: In-Patient Care | L435: 5 | M435: Neurology | N435: =IF(M435="Cardiology","Cardio",IF(M435="Intensive Care Unit","ICU",IF(M435="Neurology","Neuro",IF(M435="Emergency Room","ER",IF(M435="Pediatrics","PD",IF(M435="Surgery","Surgery",IF(M435="General Medicine","GM",IF(M435="Orthopedics","Ortho","")))))))) -> Neuro | O435: 10452.25 | P435: 6417.47 | Q435: 5.2 | R435: =IF(Patient_Data!$L435<2,"Low Risk",IF(Patient_Data!$L435<4,"Moderate Risk","High Risk")) -> High Risk | S435: =IF(Patient_Data[[#This Row],[Age]]<=18,"Pediatric",IF(Patient_Data[[#This Row],[Age]]<=64,"Adult","Geriatric")) -> Adult
A436: NHM-2026-100706 | B436: =TEXT(Patient_Data!$E436,"mmmm") -> March | C436: =LEFT(B436,3) -> Mar | D436: =MONTH(Patient_Data!$E436) -> 3 | E436: 46112 | F436: =TEXT(Patient_Data[[#This Row],[Admission_Date]],"YYYY") -> 2026 | G436: Nicole Brooks | H436: NovaHealth Northside Hospital | I436: Female | J436: 22 | K436: Readmitted | L436: 2 | M436: General Medicine | N436: =IF(M436="Cardiology","Cardio",IF(M436="Intensive Care Unit","ICU",IF(M436="Neurology","Neuro",IF(M436="Emergency Room","ER",IF(M436="Pediatrics","PD",IF(M436="Surgery","Surgery",IF(M436="General Medicine","GM",IF(M436="Orthopedics","Ortho","")))))))) -> GM | O436: 3435.83 | P436: 2270.93 | Q436: 9 | R436: =IF(Patient_Data!$L436<2,"Low Risk",IF(Patient_Data!$L436<4,"Moderate Risk","High Risk")) -> Moderate Risk | S436: =IF(Patient_Data[[#This Row],[Age]]<=18,"Pediatric",IF(Patient_Data[[#This Row],[Age]]<=64,"Adult","Geriatric")) -> Adult
A437: NHM-2023-102481 | B437: =TEXT(Patient_Data!$E437,"mmmm") -> April | C437: =LEFT(B437,3) -> Apr | D437: =MONTH(Patient_Data!$E437) -> 4 | E437: 45407 | F437: =TEXT(Patient_Data[[#This Row],[Admission_Date]],"YYYY") -> 2024 | G437: Mark Moore | H437: NovaHealth Greenfield Clinic | I437: Female | J437: 65 | K437: Readmitted | L437: 3 | M437: Intensive Care Unit | N437: =IF(M437="Cardiology","Cardio",IF(M437="Intensive Care Unit","ICU",IF(M437="Neurology","Neuro",IF(M437="Emergency Room","ER",IF(M437="Pediatrics","PD",IF(M437="Surgery","Surgery",IF(M437="General Medicine","GM",IF(M437="Orthopedics","Ortho","")))))))) -> ICU | O437: 17912.53 | P437: 12122.2 | Q437: 15.1 | R437: =IF(Patient_Data!$L437<2,"Low Risk",IF(Patient_Data!$L437<4,"Moderate Risk","High Risk")) -> Moderate Risk | S437: =IF(Patient_Data[[#This Row],[Age]]<=18,"Pediatric",IF(Patient_Data[[#This Row],[Age]]<=64,"Adult","Geriatric")) -> Geriatric
A438: NHM-2026-101735 | B438: =TEXT(Patient_Data!$E438,"mmmm") -> July | C438: =LEFT(B438,3) -> Jul | D438: =MONTH(Patient_Data!$E438) -> 7 | E438: 45482 | F438: =TEXT(Patient_Data[[#This Row],[Admission_Date]],"YYYY") -> 2024 | G438: Alexander Smith | H438: NovaHealth Lakeside Medical Center | I438: Female | J438: 53 | K438: Readmitted | L438: 3 | M438: General Medicine | N438: =IF(M438="Cardiology","Cardio",IF(M438="Intensive Care Unit","ICU",IF(M438="Neurology","Neuro",IF(M438="Emergency Room","ER",IF(M438="Pediatrics","PD",IF(M438="Surgery","Surgery",IF(M438="General Medicine","GM",IF(M438="Orthopedics","Ortho","")))))))) -> GM | O438: 6084.01 | P438: 4317.21 | Q438: 7.3 | R438: =IF(Patient_Data!$L438<2,"Low Risk",IF(Patient_Data!$L438<4,"Moderate Risk","High Risk")) -> Moderate Risk | S438: =IF(Patient_Data[[#This Row],[Age]]<=18,"Pediatric",IF(Patient_Data[[#This Row],[Age]]<=64,"Adult","Geriatric")) -> Adult
A439: NHM-2026-100267 | B439: =TEXT(Patient_Data!$E439,"mmmm") -> April | C439: =LEFT(B439,3) -> Apr | D439: =MONTH(Patient_Data!$E439) -> 4 | E439: 45764 | F439: =TEXT(Patient_Data[[#This Row],[Admission_Date]],"YYYY") -> 2025 | G439: Judy Rodriguez | H439: NovaHealth Chicago Medical Center | I439: Male | J439: 95 | K439: Readmitted | L439: 3 | M439: Intensive Care Unit | N439: =IF(M439="Cardiology","Cardio",IF(M439="Intensive Care Unit","ICU",IF(M439="Neurology","Neuro",IF(M439="Emergency Room","ER",IF(M439="Pediatrics","PD",IF(M439="Surgery","Surgery",IF(M439="General Medicine","GM",IF(M439="Orthopedics","Ortho","")))))))) -> ICU | O439: 9829.31 | P439: 7253.8 | Q439: 9.8 | R439: =IF(Patient_Data!$L439<2,"Low Risk",IF(Patient_Data!$L439<4,"Moderate Risk","High Risk")) -> Moderate Risk | S439: =IF(Patient_Data[[#This Row],[Age]]<=18,"Pediatric",IF(Patient_Data[[#This Row],[Age]]<=64,"Adult","Geriatric")) -> Geriatric
... A474: NHM-2026-102150 | B474: =TEXT(Patient_Data!$E474,"mmmm") -> February | C474: =LEFT(B474,3) -> Feb | D474: =MONTH(Patient_Data!$E474) -> 2 | E474: 46068 | F474: =TEXT(Patient_Data[[#This Row],[Admission_Date]],"YYYY") -> 2026 | G474: Timothy Mitchell | H474: NovaHealth Metro General Hospital | I474: Male | J474: 11 | K474: Discharged | L474: 2 | M474: Pediatrics | N474: =IF(M474="Cardiology","Cardio",IF(M474="Intensive Care Unit","ICU",IF(M474="Neurology","Neuro",IF(M474="Emergency Room","ER",IF(M474="Pediatrics","PD",IF(M474="Surgery","Surgery",IF(M474="General Medicine","GM",IF(M474="Orthopedics","Ortho","")))))))) -> PD | O474: 926.85 | P474: 703.8 | Q474: 3.4 | R474: =IF(Patient_Data!$L474<2,"Low Risk",IF(Patient_Data!$L474<4,"Moderate Risk","High Risk")) -> Moderate Risk | S474: =IF(Patient_Data[[#This Row],[Age]]<=18,"Pediatric",IF(Patient_Data[[#This Row],[Age]]<=64,"Adult","Geriatric")) -> Pediatric
...

Sheet Dashboard

Sheet Tools
B3: Logo
G5: `
B11: Colors
B13: Background Color | C13: #66FFCC
B14: Overlay Color | C14: #000000
B15: Cards and Charts Background | C15: #111111
